Workbook

Sheet Overview
E9: Firebird
E11: Modules | F11: TC count | G11: Pass | H11: Fail | I11: N/A | J11: Blocker
E12: Practice Setup | F12: 69 | G12: =COUNTIF(PracticeManagement!F:F,"Pass") -> 0 | H12: =COUNTIF(PracticeManagement!F:F,"Fail") -> 0 | I12: =COUNTIF(PracticeManagement!F:F,"N/A") -> 0 | J12: =COUNTIF(PracticeManagement!F:F,"Blocker") -> 0
E13: Front Desk | F13: 135 | G13: =COUNTIF(FrontDesk!J:J,"Pass") -> 0 | H13: =COUNTIF(FrontDesk!J:J,"Fail") -> 0 | I13: =COUNTIF(FrontDesk!J:J,"N/A") -> 0 | J13: =COUNTIF(FrontDesk!J:J,"Blocker") -> 0
E14: Messaging | F14: 51 | G14: =COUNTIF(Message!J:J,"Pass") -> 0 | H14: =COUNTIF(Message!J:J,"Fail") -> 0 | I14: =COUNTIF(Message!J:J,"N/A") -> 0 | J14: =COUNTIF(Message!J:J,"Blocker") -> 0
E15: Nurse | F15: 133 | G15: =COUNTIF(Nurse!H:H,"Pass") -> 0 | H15: =COUNTIF(Nurse!H:H,"Fail") -> 0 | I15: =COUNTIF(Nurse!H:H,"N/A") -> 0 | J15: =COUNTIF(Nurse!H:H,"Blocker") -> 0
E16: Billing | F16: 243 | G16: =COUNTIF(Billing!I:I,"Pass") -> 0 | H16: =COUNTIF(Billing!I:I,"Fail") -> 0 | I16: =COUNTIF(Billing!I:I,"N/A") -> 0 | J16: =COUNTIF(Billing!I:I,"Blocker") -> 0
E17: Provider | F17: 127 | G17: =COUNTIF(#REF!,"Pass") -> 0 | H17: =COUNTIF(#REF!,"Fail") -> 0 | I17: =COUNTIF(#REF!,"N/A") -> 0 | J17: =COUNTIF(#REF!,"Blocker") -> 0
E18: New calendar | F18: 79 | G18: =COUNTIF(NewCalendar!F:F,"Pass") -> 0 | H18: =COUNTIF(NewCalendar!F:F,"Fail") -> 0 | I18: =COUNTIF(NewCalendar!F:F,"N/A") -> 0 | J18: =COUNTIF(NewCalendar!F:F,"Blocker") -> 0
E19: Total | F19: =SUM(F12:F18) -> 837
E23: MySQL
E25: Modules | F25: TC count | G25: Pass | H25: Fail | I25: N/A | J25: Blocker
E26: Practice Setup | F26: 234 | G26: =COUNTIF(PracticeManagement!I:I,"Pass") -> 0 | H26: =COUNTIF(PracticeManagement!I:I,"Fail") -> 0 | I26: =COUNTIF(PracticeManagement!I:I,"N/A") -> 0 | J26: =COUNTIF(PracticeManagement!I:I,"Blocker") -> 0
E27: Front Desk | F27: 444 | G27: =COUNTIF(FrontDesk!M:M,"Pass") -> 0 | H27: =COUNTIF(FrontDesk!M:M,"Fail") -> 0 | I27: =COUNTIF(FrontDesk!M:M,"N/A") -> 0 | J27: =COUNTIF(FrontDesk!M:M,"Blocker") -> 0
E28: Messaging | F28: 184 | G28: =COUNTIF(Message!M:M,"Pass") -> 0 | H28: =COUNTIF(Message!M:M,"Fail") -> 0 | I28: =COUNTIF(Message!M:M,"N/A") -> 0 | J28: =COUNTIF(Message!M:M,"Blocker") -> 0
E29: Nurse | F29: 459 | G29: =COUNTIF(Nurse!K:K,"Pass") -> 0 | H29: =COUNTIF(Nurse!K:K,"Fail") -> 0 | I29: =COUNTIF(Nurse!K:K,"N/A") -> 0 | J29: =COUNTIF(Nurse!K:K,"Blocker") -> 0
E30: Billing | F30: 806 | G30: =COUNTIF(Billing!L:L,"Pass") -> 0 | H30: =COUNTIF(Billing!L:L,"Fail") -> 0 | I30: =COUNTIF(Billing!L:L,"N/A") -> 0 | J30: =COUNTIF(Billing!L:L,"Blocker") -> 0
E31: Provider | F31: 398 | G31: =COUNTIF(Provider!I:I,"Pass") -> 0 | H31: =COUNTIF(Provider!I:I,"Fail") -> 0 | I31: =COUNTIF(Provider!I:I,"N/A") -> 0 | J31: =COUNTIF(Provider!I:I,"Blocker") -> 0
E32: New calendar | F32: 249 | G32: =COUNTIF(NewCalendar!I:I,"Pass") -> 0 | H32: =COUNTIF(NewCalendar!I:I,"Fail") -> 0 | I32: =COUNTIF(NewCalendar!I:I,"N/A") -> 0 | J32: =COUNTIF(NewCalendar!I:I,"Blocker") -> 0
E33: Total | F33: =SUM(F26:F32) -> 2774

Sheet Split
C2: Release Type | D2: FB | E2: MySQL
C3: Feature Release | D3: High-Level Testing | E3: Full Regression Testing
C4: Maintenance Release | D4: High-Level Testing | E4: High-Level Testing
C9: Feature Release
C11: Team Member | D11: High Level Count | E11: High Level Module | F11: Full Regression Count | G11: Full Regression Module | H11: Total TC count
C12: Marcelo | D12: 64 | E12: Front Desk | F12: 143 | G12: Front Desk | H12: =sum(D12+F12) -> 207
C13: Walter | D13: 71 | E13: Front Desk | F13: 147 | G13: Front Desk | H13: =sum(D13+F13) -> 218
C14: Osmar | D14: 0 | E14: - | F14: 198 | G14: PM | H14: =sum(D14+F14) -> 198
C15: David | D15: 56 | E15: Message | F15: 185 | G15: Message | H15: =sum(D15+F15) -> 241
C16: Bruno | D16: 0 | E16: - | F16: 146 | G16: Front Desk | H16: =sum(D16+F16) -> 146
C17: Gustavo | D17: 60 | E17: Billing | F17: 160 | G17: Billing | H17: =sum(D17+F17) -> 220
C18: Thara | D18: 64 | E18: Nurse | F18: 135 | G18: Nurse | H18: =sum(D18+F18) -> 199
C19: Shalini | D19: 64 | E19: Nurse | F19: 135 | G19: Nurse | H19: =sum(D19+F19) -> 199
C20: Hari | D20: 0 | E20: - | F20: 249 | G20: New calendar | H20: =sum(D20+F20) -> 249
C21: New1 | D21: 0 | E21: - | F21: 133 | G21: Nurse | H21: =sum(D21+F21) -> 133
C22: Praveen | D22: 79 | E22: New calendar | F22: 100 | G22: Provider | H22: =sum(D22+F22) -> 179
C23: Darshan | D23: 63 | E23: Provider | F23: 99 | G23: Provider | H23: =sum(D23+F23) -> 162
... C28: Manjunath | D28: 69 | E28: PM | F28: 99 | G28: Provider | H28: =sum(D28+F28) -> 168

Sheet FrontDesk
A1: TEST SCENARIO | B1: STEPS | C1: EXPECTED RESULTS | D1: TC source | E1: HighLevel | F1: Owner - FB(High level) | G1: Status | H1: Comment | I1: Owner - MySQL(Full regression) | J1: Status | K1: Comments
A2: Login: Show a popup when the user enters the wrong password
A3: Verify below warning popup shows up, when user login OP with wrong username and password. "Incorrect username and password". | B3: 1. Open the OP application. 2. Enter wrong Username and Password. 3. Click Login button. 4. Check below warning popup shows up, when user login OP with wrong username and password. "Incorrect username and password". | C3: Below warning popup should shows up. "Incorrect username and password". | D3: Insprint | E3: Yes | F3: Marcelo | I3: Marcelo
A4: Verify below warning popup shows up, when user login OP with wrong username and correct password. "Incorrect username and password". | B4: 1. Open the OP application. 2. Enter wrong Username and correct Password. 3. Click Login button. 4. Check below warning popup shows up, when user login OP with wrong username and correct password. "Incorrect username and password". | C4: Below warning popup should shows up. "Incorrect username and password". | D4: Insprint | E4: Yes | F4: Walter | I4: Walter
A5: Verify below warning popup shows up, when user login OP with correct username and wrong password. "Incorrect username and password". | B5: 1. Open the OP application. 2. Enter correct Username and wrong Password. 3. Click Login button. 4. Check below warning popup shows up, when user login OP with correct username and wrong password. "Incorrect username and password". | C5: Below warning popup should shows up. "Incorrect username and password". | D5: Insprint | E5: Yes | F5: Marcelo | I5: Marcelo
A6: Verify below warning popup shows up, when user enters special characters in username and password to login OP. "Incorrect username and password". | B6: 1. Open the OP application. 2. Enter special characters in Username and Password. 3. Click Login button. 4. Check below warning popup shows up, when user enters special characters in username and password to login OP. "Incorrect username and password". | C6: Below warning popup should shows up. "Incorrect username and password". | D6: Insprint | E6: Yes | F6: Walter | I6: Walter
A7: Verify the cursor is auto-focused(i.e. cursor should placed in the username box) in the username box. when user login OP with wrong username and password and accepts the warning popup "Incorrect username and password" . | B7: 1. Open the OP application. 2. Enter wrong Username and Password. 3. Click Login button. 4. The "Incorrect username and password" waring popup shows up. 5. Accept the warning popup. 6. Check the cursor is auto-focused(i.e. cursor should placed in the username box) in the username box. | C7: The cursor should auto-focused(i.e. cursor should placed in the username box) in the username box. | D7: Insprint | E7: Yes | F7: Marcelo | I7: Marcelo
A8: Login box should not disappear, when user clicks on cancel button. | B8: 1. Open the OP application. 2. Enter Username and Password. 3. Click Cancel button instead of clicking Login button. 4. Check Login box should not disappear, only the data entered in username and password should disappear. | C8: Login box should not disappear, only the data entered in username and password should be disappear. | D8: RelaseFilter | E8: Yes | F8: Walter | I8: Walter
A9: Verify the choose location pop window has been displayed, when user try to login the application for first time in a day. | B9: First time in a day 1. Launch the op application 2. enter the user name and password 3. Click login button 4. Check the Choose location pop up window is popup. 5. Select the valid location and click ok button. | C9: Choose Location pop up window should be displayed | D9: Exploratory | I9: Marcelo
A10: Verify the choose location pop window is not displayed, when the same user try to login the application for second time in a day. | B10: Second time in a day 1. Launch the op application 2. without enter the user name and password 3. Click login button 4. Observe Choose location pop window will not come for second time login in a day 5. Navigate to dashboard | C10: Choose Location pop window should not displayed for second time login in a day | D10: Exploratory | I10: Walter
A11: Verify user able to select the location | B11: First time in a day 1. Launch the op application 2. enter the user name and password 3. Click login button 4. Check the Choose location pop up window is popup. 5. Select the valid location and click ok button. | C11: Application should be launched the home page | D11: Exploratory | I11: Marcelo
A12: Verify user not able to access the dashboard without selecting any location | B12: Location popup will come only first time in a day 1. Launch the op application 2. without enter the user name and password 3. Click login button 4. location pop up window will come 4. Not selecting the location 5. Click cancel button. 6. Check the user not able to login and user remains to login page . | C12: Application should be throw an error message and reopen the login page window. | D12: Exploratory
A13: Access and Navigate to the schedule Window
A14: Verify user able to access the schedule window by clicking on schedule icon | B14: 1. launch the OP application 2. Select the clinical tab in the top-left corner of the window. 3. Click Schedule Icon. | C14: Schedule Window should appear. | E14: Yes | F14: Marcelo | I14: Marcelo
A15: Verify user can able to view appointment window | B15: 1. Login to the OP 2. Navigate to Practice Management > Schedule > calender window 3. Double click to add an appointment 4. Check user able to view the appointment window | C15: User should view the appointment window | D15: Insprint | I15: Walter
A16: Verify "Prim/alt phone" is removed | B16: 1. Login to the OP 2. Navigate to Practice Management > Schedule > calender window 3. Double click to add an appointment 4. Ensure the appointment window open 5. Check there is no "Prim/alt phone:" field | C16: User should not view "Prim/alt phone:" field | D16: Insprint | I16: Marcelo
A17: Verify Curbside has been left aligned | B17: 1. Login to the OP 2. Navigate to Practice Management > Schedule > calendar window 3. Double click to add an appointment 4. Ensure"Curbside" field located in left side | C17: User should view the "Curbside" field located in left side | D17: Insprint | I17: Marcelo
A18: Verify user can able to view new patient header | B18: 1. Login to the OP. 2. Navigate to Practice Management > Schedule > calender window. 3. Double click to add an appointment. 4. Check the appointment window visible. 5. Search a patient. 6. Check user can able to view the new patient header. | C18: User should view the new patient header | D18: Insprint | I18: Marcelo
A19: Verify user can able to view pencil button next to the patient name | B19: 1. Login to the OP 2. Navigate to Practice Management > Schedule > calender window 3. Double click to add an appointment. 4. Ensure the add appointment window visible. 5. Search a patient. 6. Check user can able to view pencil button is visible. | C19: User should view pencil button. | D19: Insprint
A20: Verify user can see the correct placement of the Search button, Last encounter, Last well visit, and Portal Account information | B20: 1. Login to the OP 2. Navigate to Practice Management > Schedule > calender window 3. Double click to add an appointment 4. Ensure the add appointment window visible 5. Search a patient 6. Cheeck user able to see the correct placement of the Search button, Last encounter, Last well visit, and Portal Account information | C20: User should see the correct placement of the Search button, Last encounter, Last well visit, and Portal Account information | D20: Insprint | I20: Marcelo
A21: Verify user can see labels above the Misc. Notes and Billing Notes grid | B21: 1. Login to the OP 2. Navigate to Practice Management > Schedule > calender window 3. Double click to add an appointment 4. Ensure the add appointment window visible 5. Check user can view the labels above the Misc. Notes and Billing Notes grid | C21: User should see the labels above the Misc. Notes and Billing Notes grid. | D21: Insprint | I21: Marcelo
A22: Verify user can abe to see the Blank Patient Photo | B22: 1. Login to the OP 2. Navigate to Practice Management > Schedule > calender window 3. Double click to add an appointment 4. Check the add appointment window visible 5. Search a patient 6. Check user can view the Blank Patient Photo. | C22: User should view the Blank Patient Photo. | D22: Insprint | I22: Marcelo
A23: Verify User can able to view 2 radio button options "Patient" and "Family Contact" on full patient search window | B23: 1.Log into OP 2. Navigate to Clinical > Practice Management > Billing 3. Click the patient chart 4. Click the Full Search Icon(Patient Finder icon) make sure the full patient search window is opened 5. look at the top of the window 6. Make sure the user can see 2 radio button options 'Patient' and 'Family Contact' | C23: User should view 2 radio button options "Patient" and "Family Contact" on full patient search window | D23: RelaseFilter | I23: Bruno
A24: Verify Patient radio button is selected by default on full patient search window. | B24: 1. Log into OP 2. Navigate to Clinical > Practice Management > Billing 3. Click the patient chart 4. Click the Full Search Icon(Patient Finder icon) make sure the full patient search window is opened 5. look at the top of the window 6. Make sure the user can see Patient radio button is selected by default | C24: The Patient radio button should selected by default on full patient search window. | D24: RelaseFilter | I24: Bruno
A25: Verify User can able to Search for a patient by using the Patient Radio Button for the below-mentioned field on the full patient search window and verify the grid displays searched patient. Last Name First Name DOB PatNo Alt phone | B25: 1. Log into OP 2. Navigate to Clinical > Practice Management > Billing 3. Click the patient chart 4. Click the Full Search Icon(Patient Finder icon) make sure the full patient search window is opened 5. Make sure the patient radio button is selected in the full patient search window 6. Enter In the (Last Name, First Name, DOB, PatNo, Alt, phone )search criteria 7. Make sure the results of patients meet the criterion selected. | C25: User Should search a patient by using the Patient Radio Button for the below-mentioned field on the full patient search window and the grid should displays searched patient. Last Name First Name DOB PatNo Alt phone | D25: RelaseFilter | I25: Bruno
A26: Verify that when the "Family Contact" radio button is selected, the "PatNo", "DOB", and "Alt Name" fields are disabled on the full patient search window. | B26: 1. Log into OP 2. Navigate to Clinical > Practice Management > Billing 3. Click the patient chart 4. Click the "Full Search" icon to ensure the full patient search window is opened 5. Ensure the "Family Contact" radio button is selected in the full patient search window 6. Review the search criteria fields 7. Confirm that the "PatNo", "DOB", and "Alt. Name" fields are disabled as they are not applicable to Family Contact | C26: Users should observe that the "PatNo", "DOB", and "Alt. Name" fields are disabled on the full patient search window when the "Family Contact" radio button is selected. | D26: RelaseFilter | I26: Bruno
A27: Verify that the user can search for a patient using the "Family Contact" radio button for the following fields on the full patient search window and confirm that the grid displays the searched patient: - Last Name - First Name - Phone | B27: 1. Log into OP 2. Navigate to Clinical > Practice Management > Billing 3. Click the patient chart 4. Click the "Full Search" icon (Human icon) to ensure the full patient search window is opened 5. Ensure the "Family Contact" radio button is selected in the full patient search window 6. Enter the search criteria for (Last Name, First Name, Phone) 7. Confirm that the results display patients with linked family contacts meeting the selected criteria | C27: User should search for a patient by using the "Family Contact" radio button for the following fields on the full patient search window and verify the grid displays patients with linked family contacts meeting the selected criteria: - Last Name - First Name - Phone | D27: RelaseFilter | I27: Bruno
A28: Verify that the user can save the "Family Contact" radio button as a preference on the full patient search window. | B28: 1. Log into OP 2. Navigate to Clinical > Practice Management > Billing 3. Click the patient chart 4. Click the "Full Search" icon (Patient Finder icon) to ensure the full patient search window is opened 5. Select the "Family Contact" Radio Button in the full patient search window 6. Click "Save Preference" 7. Close and reopen the OP application 8. Verify that the "Family Contact" radio button is selected by default | C28: User should save the "Family Contact" Radio Button as a preference on the full patient search window. | D28: RelaseFilter | I28: Bruno
A29: Verify the functionality of the alphabet tabs to match the current functionality on the full patient search window. | B29: 1. Log into OP 2. Navigate to Clinical > Practice Management > Billing 3. Click the patient chart 4. Click the "Full Search" icon (Human icon) to ensure the full patient search window is opened 5. Select the "Family Contact" radio button in the full patient search window 6. Click any of the alphabet buttons at the bottom of the window 7. Verify that only patients with linked family contacts, whose last names begin with the pressed letter, are displayed in the search window | C29: The functionality of the alphabet tabs should match the current functionality on the full patient search window. | D29: RelaseFilter | I29: Bruno
A30: Verify user can Search results for family contact on the full patient search window | B30: 1. Log into OP 2. Navigate to Clinical > Practice Management > Billing 3. Click the patient chart 4. Click the "Full Search" icon (Patient Finder icon) to ensure the full patient search window is opened 5. Select the "Family Contact" radio button in the full patient search window 6. Search using any enabled search criteria fields 7. Verify that patients with linked family contacts meeting the selected criteria are shown first, followed by patients who meet the criteria in the list of results | C30: User should search results for family contact on the full patient search window. | D30: RelaseFilter | I30: Bruno
A31: Verify that entering 10 digits and hitting ENTER shows all phone numbers meeting that criteria, regardless of whether dashes are stored or not in the Patient database. | B31: 1. Log into OP 2. Open Patient Chart 3. Click the Search Icon to open the advanced search 4. Select the "Patient" radio button 5. Enter a 10-digit phone number 6. Press ENTER 7. Verify that all patients with the entered 10-digit phone number are displayed, regardless of whether there are hyphens or not. | C31: The user should press ENTER and view 10 digits of phone numbers meeting that criteria, regardless of whether dashes are stored or not in the Patient database. | D31: RelaseFilter | I31: Bruno
... A68: Verify that the user can see an alert on save when the Phone field is blank but an Extension exists on Demographics. NOTE - Repeat for Family Contacts | B68: 1. Log in to the OP application. 2. Navigate to any one of the tabs Clinical / Practice Management / Billing. 3. Select a patient's chart. 4. Go to Basic Information to open the Demographics. 5. Look next to Day/Work; you see a small extension field. 6. Enter an Extension and no Day/Work number. 7. Click Save. 8. Verify you get an alert: "Day/Work number is required when an extension is present." NOTE - Repeat for Family Contacts | C68: User should see an alert on Save when the Phone field is blank but Extension exists on Demographics. NOTE - Repeat for Family Contacts | D68: Insprint | I68: Bruno
A69: Check if the shortcut key "Function + F7" opens the schedule window. | B69: 1. Launch the OP application. 2. Select the Clinical tab. 3. Press the F7 key. | C69: The Schedule Window should appear. | I69: Walter
A70: Verify that the No Show* Billing Status does not add a Miscellaneous Note. | B70: 1. Launch OP. 2. Open the Schedule. 3. Schedule an appointment. 4. Click Save. 5. Double click on the appointment to edit. 6. Click the Billing Status dropdown. 7. Select 'No Show*'. 8. Click Save. 9. Open the Patient's chart. 10. Open Clinical Overview. 11. Verify they do not see a miscellaneous note stating "@No Show- Today's Date". | C70: User should not be able to add a Miscellaneous Note by using the No Show* Billing Status. | D70: Insprint | I70: Walter
A71: Verify that the No Show Billing Status does add a Miscellaneous Note. | B71: 1. Launch OP. 2. Open the Schedule. 3. Schedule an appointment. 4. Click Save. 5. Double click on the appointment to edit. 6. Click the Billing Status dropdown. 7. Select 'No Show'. 8. Click Save. 9. Open the Patient's chart. 10. Open Clinical Overview. 11. Verify they do see a miscellaneous note stating "@No Show- Today's Date". | C71: User should be able to see a miscellaneous note stating '@No Show- Today's Date'. | D71: Insprint | I71: Walter
A72: Verify that when one user is scheduling an appointment, another user should see a 'Scheduling in progress' bar on the time slot. | B72: 2 different users need to be logged into OP to test. Both users: 1. Log into OP. 2. Open the Calendar schedule for Demo Doctor. User 1: 1. Double click on a time slot to open the Add/Edit appointment window. User 2: 1. User 2 should see a "Scheduling in progress" bar on the time slot where an appointment is being scheduled. NOTE- Try with 3-5 other users logged in as well to make sure all users see the "Scheduling in progress" bar. | C72: Users should see that when one user is scheduling an appointment, another user should see the "Scheduling in progress" bar on the time slot. | D72: RelaseFilter | I72: Marcelo
A73: Verify that when one user adds an appointment to the schedule, all other users can see the 'appointment' on the same day and provider in the calendar schedule. | B73: 2 different users need to be logged into OP to test. Both users: 1. Log into OP. 2. Open the Calendar schedule for Demo Doctor. User 1: 1. Double click on a time slot to open the Add/Edit appointment window. 2. Finish scheduling appointment and click Save. User 2: 1. User 2 should see a "Scheduling in progress" bar on the time slot where an appointment is being scheduled. 2. User 2 should see the appointment appear on the schedule. | C73: Users should see that when one user adds an appointment to the schedule, all other users should see the 'appointment' on the same day and provider in the calendar schedule. | D73: RelaseFilter | I73: Marcelo
A74: Verify that when one user updates the visit status on an appointment, other users see the appointment block color update on the schedule. | B74: 2 different users need to be logged into OP to test. Both users: 1. Log into OP. 2. Open the Calendar schedule for Demo Doctor. User 1: 1. Schedule an appointment and close the Add/Edit appointment window. User 2: 1. User 2 should see a "Scheduling in progress" bar and the appointment appear on the time slot where an appointment is being scheduled. User 1: 1. Double click on the appointment and update the visit status. 2. Save and Exit. User 2: 1. User 2 should see that the appointment color changes based on the appointment status chosen. NOTE - Try with 3-5 other users logged in as well to make sure all users see the appointment update. | C74: When one user updates the visit status on an appointment, verify that other users see the appointment block color update on the schedule. | D74: RelaseFilter | I74: Marcelo
A75: Verify that when one user adds a copay in the Add/Edit appointment window, other users see the copay label on the appointment on the schedule. | B75: 2 different users need to be logged into OP to test. Both users: 1. Log into OP. 2. Open the Calendar schedule for Demo Doctor. User 1: 1. Schedule an appointment and close the Add/Edit appointment window. User 2: 1. User 2 should see a "Scheduling in progress" bar and the appointment appear on the time slot where an appointment is being scheduled. User 1: 1. Double click on the appointment and click on the credit button next to the Payment Received field. 2. Enter the payment information (Payment method, Patient amount). 3. Click Save/Post. User 2: 1. User 2 should see that the appointment is updated with the Copay box. NOTE - Try with 3-5 other users logged in as well to make sure all users see the appointment update. | C75: When one user adds a copay in the Add/Edit appointment window, other users should see the copay label on the appointment on the schedule. | D75: RelaseFilter | I75: Marcelo
A76: 1) Verify that when one user adds the flags (WHITE, GREEN, RED) to an appointment, all other users are able to see the flags (WHITE, GREEN, RED) on the same day and provider in the calendar schedule. 2) "Verify that when one user removes the flags (WHITE, GREEN, RED) from an appointment, the flags (WHITE, GREEN, RED) have been removed from the appointment for all other users on the same day and provider in the calendar schedule. | B76: 2 different users need to be logged into OP to test. Both users: 1. Log into OP. 2. Open the Calendar schedule for Demo Doctor. User 1: 1. Schedule an appointment and close the Add/Edit appointment window. User 2: 1. User 2 should see a "Scheduling in progress" bar and the appointment appear on the time slot where an appointment is being scheduled. User 1: 1. Click on the appointment and click on the green flag. The green flag will appear on the appointment. 2. User 2 should see that the appointment is updated with the green flag. User 1: 1. Click on the appointment and click on the blank flag. The green flag will disappear from the appointment. 2. User 2 should see that the appointment is updated with the removal of the green flag. User 1: 1. Click on the appointment and click on the red flag. The red flag will appear on the appointment. 2. User 2 should see that the appointment is updated with the red flag. User 1: 1. Click on the appointment and click on the blank flag. The red flag will disappear from the appointment. 2. User 2 should see that the appointment is updated with the removal of the red flag. NOTE - Try with 3-5 other users logged in as well to make sure all users see the appointment update. | C76: 1) When one user adds the flags (WHITE, GREEN, RED) to an appointment, all other users should see the flags (WHITE, GREEN, RED) on the same day and provider in the calendar schedule. 2) When one user removes the flags (WHITE, GREEN, RED) from an appointment, the flags (WHITE, GREEN, RED) should be removed from the appointment for all other users on the same day and provider in the calendar schedule. | D76: RelaseFilter | I76: Marcelo
A77: 1. Verify that when one user adds a tentative '?' to the appointment, all other users can see the tentative '?' on the appointment for the same day and provider in the calendar schedule. 2. Verify that when one user removes the tentative '?' from the appointment, it is removed for all other users on the appointment for the same day and provider in the calendar schedule. | B77: 2 different users need to be logged into OP to test. Both users: 1. Log into OP. 2. Open the Calendar schedule for Demo Doctor. User 1: 1. Schedule an appointment and close the Add/Edit appointment window. User 2: 1. User 2 should see a "Scheduling in progress" bar and the appointment appear on the time slot where an appointment is being scheduled. User 1: 1. Click on the appointment and click on the tentative '?' button. The '?' will appear on the appointment. 2. User 2 should see that the appointment is updated with the '?'. User 1: 1. Click on the appointment and click on the '?' tentative button again. The '?' will disappear from the appointment. 2. User 2 should see that the appointment is updated with the removal of the '?'. NOTE - Try with 3-5 other users logged in as well to make sure all users see the appointment update. | C77: When one user adds a tentative '?' to the appointment, all other users should see the tentative '?' on the appointment for the same day and provider in the calendar schedule. When one user removes the tentative '?' from the appointment, the "?" icon should removed for all other users on the appointment for the same day and provider in the calendar schedule. | D77: RelaseFilter | I77: Marcelo
A78: Verify that the user can change the status color to the Billing Stage radio button on the Tracking screen under the Schedule window. | B78: 1. Log on to OP with valid credentials. 2. Navigate to Schedule under the Billing tab. 3. Ensure the user navigates to the Schedule window. 4. Click on the Tracking radio button. 5. Click the down arrow next to Settings. 6. Select the Billing Stage radio button in Status Color. 7. After the user clicks out of the dropdown, the Settings field refreshes and shows the changes. | C78: User should be able to change the status color to Billing Stage. | D78: Insprint | I78: Marcelo
A79: Verify that the user can change the status color to the Visit Stage radio button on the Tracking screen under the Schedule window. | B79: 1. Log on to OP with valid credentials. 2. Navigate to Schedule under the Billing tab. 3. Ensure the user navigates to the Schedule window. 4. Click on the Tracking radio button. 5. Click the down arrow next to Settings. 6. Select the Visit Stage radio button in Status Color. 7. After the user clicks out of the dropdown, the Settings field refreshes and shows the changes. | C79: User should be able to change the status color to Visit Stage. | D79: Insprint | I79: Marcelo
A80: Verify that the user is able to view the Disable setting in Global Preferences under Schedule on System Preference, affecting all users on the network. | B80: 1. Log on to OP with valid credentials. 2. Navigate to Admin Tab > Global Preference > Schedule. 3. Ensure the user is able to see "Disable no show appointment status from the auto creating a miscellaneous notes". | C80: User is able to see 'Disable no show appointment status from the auto creating a miscellaneous notes'. | D80: Insprint | I80: Marcelo
A81: Verify that the user is able to check the 'Disable No Show' setting. | B81: 1. Log on to OP with valid credentials. 2. Navigate to Admin Tab > Global Preference > Schedule. 3. Ensure the user is able to see "Disable no show appointment status from the auto creating a miscellaneous notes". 4. Check the "Disable no show appointment status from the auto creating a miscellaneous notes" checkbox. 5. Click Exit. 6. Log out and log back in. 7. Navigate to Schedule > Calendar Schedule. 8. While making an appointment for the patient, click on the Billing Status dropdown and select "NO SHOW". 9. Click Save. 10. Navigate to the patient's chart for the added appointment. 11. Navigate to the Clinical Overview tab. 12. Ensure the Miscellaneous Notes field is empty. | C81: User should see the Miscellaneous Notes field as EMPTY under the Patient Chart. | D81: Insprint | I81: Marcelo
... A83: Verify that the user is able to uncheck the 'Disable No Show' setting. | B83: 1. Log on to OP with valid credentials. 2. Navigate to Admin Tab > Global Preference > Schedule. 3. Ensure the user is able to see "Disable no show appointment status from the auto creating a miscellaneous notes". 4. Uncheck the "Disable no show appointment status from the auto creating a miscellaneous notes" checkbox. 5. Click Exit. 6. Log out and log back in. 7. Navigate to Schedule > Calendar Schedule. 8. While making an appointment for the patient, click on the Billing Status dropdown and select "NO SHOW". 9. Click Save. 10. Verify that the user sees the Miscellaneous Notes field as NOT EMPTY under the Patient Chart. | C83: User should see the Miscellaneous Notes field as NOT EMPTY under the Patient Chart. | D83: Insprint | I83: Marcelo
A84: Verify that the user is unable to remove old miscellaneous notes when the setting is disabled. | B84: 1. Log on to OP with valid credentials. 2. Navigate to Admin Tab > Global Preference > Schedule. 3. Ensure the user is able to see "Disable no show appointment status from the auto creating a miscellaneous notes". 4. Uncheck the "Disable no show appointment status from the auto creating a miscellaneous notes" checkbox. 5. Click Exit. 6. Double click on Miscellaneous Notes under the patient chart. 7. The "Patient Register: Notes and Coordination of Care" window opens. 8. Clear the miscellaneous notes and click Save. 9. Refresh the page. 10. Verify that the miscellaneous notes is NOT removed. | C84: User should be unable to remove miscellaneous notes under the Patient Chart. | D84: Insprint
A85: Verify that the user is able to access the My View and Office View in the Schedule window. | B85: 1. Launch the OP application. 2. Select the Clinical tab in the top-left corner of the window. 3. Click on the Schedule icon. 4. Select the My View and Office View. | C85: My View and Office View should appear based on user selection. | E85: Yes | F85: Marcelo | I85: Marcelo
A86: Verify that the user is able to access the locations in the Schedule window. | B86: 1. Launch the OP application. 2. Select the Clinical tab in the top-left corner of the window. 3. Click on the Schedule icon. 4. Select the My View option and click the location dropdown (i.e., Down arrow). 5. User can select the location (Primary location & Secondary location) based on their needs. | C86: The Primary location & Secondary location window should appear based on user selection in the location dropdown. | E86: Yes | F86: Marcelo | I86: Marcelo
A87: Verify that the staff and rooms are available for both the My View and Office View. | B87: 1. Launch the OP application. 2. Select the Clinical tab in the top-left corner of the window. 3. Click on the Schedule Icon. 4. Select the My View and Office View, and make sure the "Staffs and Room" button is next to the Print button. | C87: The Staff and Room button should be available for both the My View and Office View. | I87: Bruno
A88: Verify that the appointments are listed based on staff by clicking on Staff. | B88: 1. Launch the application. 2. Click on the Clinical section. 3. Click on the Schedule icon. 4. Click on the Staff icon which is present next to the Print icon. 5. Make sure the appointments are listed based on staff in My View and Office View. | C88: Existing and newly created appointments should be listed based on staff by clicking on Staff. | I88: Bruno
A89: Verify that the appointments are listed based on the rooms by clicking on Rooms. | B89: 1. Launch the application. 2. Click on the Clinical section. 3. Click on the Schedule icon. 4. Click on the Rooms icon which is present next to the Print icon. 5. Make sure the appointments are listed based on rooms in My View and Office View. | C89: Existing and newly created appointments should be listed based on staff by clicking on Staff. | I89: Bruno
A90: "Verify the popup as below appears when creating a patient in the Add Appointment window: 'New patient ID <patientID>created. Please open the chart at your earliest opportunity and complete the rest of the demographic information.'" | B90: 1. Launch the application. 2. Click on the Clinical section. 3. Click on the Schedule icon. 4. Right-click the calendar and select the "Add Appointments" option. 5. Click on the "Add Patient" button from the add/edit appointment screen. 6. Fill the required fields and click on the Save button. 7. Make sure the popup is displayed and click on OK. | C90: The popup should display the following message when creating a patient in the Add Appointment window: "New patient ID <patientID>created. Please open the chart at your earliest opportunity and complete the rest of the demographic information." | I90: Bruno
A91: Verify that the user is able to add providers (Doctors) in the My View/Office View. | B91: 1. Launch the OP application. 2. Select the Clinical tab in the top-left corner of the window. 3. Click on the Schedule Icon. 4. Select the My View option and click the location dropdown (i.e., Down arrow). 5. Choose the primary location. 6. Click the Properties button on the right side of the schedule window, and the Schedule Property window should open. 7. Add the provider to the calendar by using drag and drop or double-click. 8. Click the OK button. | C91: Provider or doctor should be added to the calendar. | E91: Yes | F91: Marcelo | I91: Marcelo
A92: Verify that the user is able to modify the calendar display preferences in the Schedule Property window. | B92: 1. Launch the OP application. 2. Select the Clinical tab in the top-left corner of the window. 3. Click on the Schedule Icon. 4. Select the My View option and click the location dropdown (i.e., Down arrow). 5. Choose the primary location. 6. Click the Properties button on the right side of the schedule window, and the Schedule Property window should open. 7. Add the provider to the calendar by using drag and drop or double-click. 8. Click the Display Preference tab. 9. Modify the columns based on provider selection (If user chooses 2 providers then select 2 in the column). 10. Modify the Time units, Line height, Appointment font, Non-prime time, and prime time. | C92: Based on the preference settings, the calendar appearance should be displayed. | E92: Yes | F92: Marcelo | I92: Marcelo
A93: Verify that the staff can set the Non-Prime Time and Prime Time in the Display Preferences window. | B93: 1. Launch the OP application. 2. Select the Clinical tab in the top-left corner of the window. 3. Click on the Schedule Icon. 4. Select the My View option and click the location dropdown (i.e., Down arrow). 5. Choose the primary location. 6. Click the Properties button on the right side of the schedule window, and the Schedule Property window should open. 7. Click on the Display Preferences tab. 8. Set the Prime Time of the staff and save the settings. 9. Make sure the Prime Time of the staff are reflected in the My Office View. | C93: Staff should be able to configure Non-Prime and Prime time settings for the staff in the My Schedule window. | E93: Yes | F93: Marcelo | I93: Marcelo
A94: Verify that the Reset button clears the entered values in the Display Preferences window. | B94: 1. Launch the OP application. 2. Select the Clinical tab in the top-left corner of the window. 3. Click on the Schedule Icon. 4. Select the My View option and click the location dropdown (i.e., Down arrow). 5. Choose the primary location. 6. Click the Properties button on the right side of the schedule window, and the Schedule Property window should open. 7. Click on the Display Preferences tab. 8. Set the Non-Prime Time and Prime Time of the staff and save the settings. 9. Click on the Reset button. 10. Verify that the field values are cleared to default. | C94: Staff should be able to reset the values in the Display Preferences window. | E94: Yes | F94: Marcelo | I94: Marcelo
A95: Verify that the confirm popup is displayed when clicking on 'OK' in the Schedule Property window. | B95: 1. Launch the OP application. 2. Select the Clinical tab in the top-left corner of the window. 3. Click on the Schedule Icon. 4. Select the My View option and click the location dropdown (i.e., Down arrow). 5. Choose the primary location. 6. Click the Properties button on the right side of the schedule window, and the Schedule Property window should open. 7. Click on the Display Preferences tab. 8. Set the Non-Prime Time and Prime Time of the staff and save the settings. 9. Verify that the popup is displayed. | C95: The confirm popup should be displayed when clicking on the 'OK' button from the Preferences window. | E95: Yes | F95: Marcelo | I95: Marcelo
A96: Verify that the user is able to view the appointments based on date/month range by using the calendar in the schedule window. | B96: 1. Launch the OP application. 2. Select the Clinical tab in the top-left corner of the window. 3. Click on the Schedule Icon. 4. Select the My View option and click the location dropdown (i.e., Down arrow). 5. Choose the primary location. 6. Select the date range in the calendar to view the appointments. | C96: Once the user clicks the date range in the calendar, the appointments should display based on the selected date/month range. | E96: Yes | F96: Marcelo | I96: Marcelo
A97: Verify that the user is able to print the appointments. | B97: 1. Launch the OP application. 2. Select the Clinical tab in the top-left corner of the window. 3. Click on the Schedule Icon. 4. Select the My View option and click the location dropdown (i.e., Down arrow). 5. Choose the primary location. 6. Click the Print button in the schedule window. 7. Enter the requirements in the Schedule Report Options. | C97: The user should be able to print the appointments. | E97: Yes | F97: Marcelo | I97: Marcelo
A98: Verify that the summary report of patients is displayed based on the number of occurrences of each patient. | B98: 1. Launch the OP application. 2. Select the Clinical tab in the top-left corner of the window. 3. Click on the Schedule Icon. 4. Select the My View option and click the location dropdown (i.e., Down arrow). 5. Choose the primary location. 6. Click the Print button in the schedule window. 7. Click on the Summary Report tab and ensure the data is displayed. 8. For 0 occurrences, the following message should be displayed: "This report shows the number of occurrences of appointment categories for staff IDs and date range." | C98: The summary report should be displayed for the patient based on the number of occurrences.
A99: Verify that the user is able to see the appointments for the day and week range. | B99: 1. Launch the OP application. 2. Select the Clinical tab in the top-left corner of the window. 3. Click on the Schedule Icon. 4. Select the My View option and click the location dropdown (i.e., Down arrow). 5. Choose the primary location. 6. Select the day and week range in the calendar. | C99: The appointments should display based on the selected day and week range. | E99: Yes | F99: Marcelo | I99: Marcelo
A100: Check if the staff member is mandatory for the week range. | B100: 1. Launch the OP application. 2. Select the Clinical tab in the top-left corner of the window. 3. Click on the Schedule Icon and click the Calendar radio button. 4. Select the Office View option and click the location dropdown (i.e., Down arrow). 5. Choose the primary location. 6. Click on the Week button. 7. Verify that a warning popup shows up to select a staff member to view the calendar in the week range. | C100: The warning popup should show up prompting the user to select a staff member to view the calendar in the week range. | E100: Yes | F100: Marcelo | I100: Marcelo
A101: Verify that the user is able to use the "Today Date" option in the calendar. | B101: 1. Launch the OP application. 2. Select the clinical tab in the top-left corner of the window. 3. Click on the Schedule icon. 4. Choose the "My View" option and click the location dropdown (i.e., the down arrow). 5. Select the primary location. 6. Choose the desired future dates. 7. Click on the "Today Date" option in the calendar. | C101: The date range should display default today's date. | E101: Yes | F101: Marcelo | I101: Marcelo
A102: Verify that the user is able to access the following icons in the schedule window: 1. Add -> Used to add a new appointment. 2. Edit -> Used to edit an appointment. 3. Delete -> Used to delete an appointment. 4. Copy -> Used to copy an appointment. 5. Move -> Used to move an appointment. | B102: 1. Launch the OP application. 2. Select the clinical tab in the top-left corner of the window. 3. Click on the Schedule Icon. 4. Choose the "My View" option and click the location dropdown (i.e., the down arrow). 5. Select the primary location. 6. Access the following icons: Add, Edit, Delete, Copy, Move. | C102: The user should be able to access the Add, Edit, Delete, Copy, and Move buttons. | E102: Yes | F102: Marcelo | I102: Marcelo
A103: Verify that the user is able to access the Calendar setting dropdown. | B103: 1. Launch the OP application. 2. Select the clinical tab in the top-left corner of the window. 3. Click on the Schedule Icon. 4. Choose the "My View" option and click the location dropdown (i.e., the down arrow). 5. Select the primary location. 6. Click on the calendar setting dropdown. | C103: The setting dropdown list should display. | E103: Yes | F103: Marcelo | I103: Marcelo
A104: Verify that the user selects the "Not assigned" option under "Show Columns" in the calendar setting dropdown. | B104: 1. Launch the OP application. 2. Select the clinical tab in the top-left corner of the window. 3. Click on the Schedule Icon. 4. Choose the "My View" option and click the location dropdown (i.e., the down arrow). 5. Select the primary location. 6. Click on the calendar setting dropdown. 7. Select the "Not assigned" option. | C104: The calendar view should display based on the "Not assigned" status. | E104: Yes | F104: Marcelo | I104: Marcelo
A105: Verify that the user selects the "Out of office" option under "Show Columns" in the calendar setting dropdown. | B105: 1. Launch the OP application. 2. Select the clinical tab in the top-left corner of the window. 3. Click on the Schedule Icon. 4. Choose the "My View" option and click the location dropdown (i.e., the down arrow). 5. Select the primary location. 6. Click on the calendar setting dropdown. 7. Select the "Out of office" option. | C105: The calendar view should display based on the "Out of office" status. | E105: Yes | F105: Marcelo | I105: Marcelo
A106: Verify that the user selects the "Visit Stage" option under "Status Columns" in the calendar setting dropdown. | B106: Pre condition: The appointment should have visit status. 1. Launch the OP application. 2. Select the clinical tab in the top-left corner of the window. 3. Click on the Schedule Icon. 4. Choose the "My View" option and click the location dropdown (i.e., the down arrow). 5. Select the primary location. 6. Click on the calendar setting dropdown. 7. Select the "Visit Stage" option. | C106: The calendar view should display based on the "Visit Stage" status. The colour will be changed based on the option selected in the visit status during adding an apt | E106: Yes | F106: Marcelo | I106: Marcelo
A107: Verify that the user selects the "Billing Stage" option under "Status Columns" in the calendar setting dropdown. | B107: Pre condition: The appointment should have Billing stage. 1. Launch the OP application. 2. Select the clinical tab in the top-left corner of the window. 3. Click on the Schedule Icon. 4. Choose the "My View" option and click the location dropdown (i.e., the down arrow). 5. Select the primary location. 6. Click on the calendar setting dropdown. 7. Select the "Billing Stage" option. | C107: The calendar view should display based on the "Billing Stage" status. The colour will be changed based on the option selected in the Billing Stage during adding an apt | E107: Yes | F107: Marcelo | I107: Marcelo
A108: Verify that the user selects the "Details" option under "Schedule Text" in the calendar setting dropdown. | B108: 1. Launch the OP application. 2. Select the clinical tab in the top-left corner of the window. 3. Click on the Schedule Icon. 4. Choose the "My View" option and click the location dropdown (i.e., the down arrow). 5. Select the primary location. 6. Click on the calendar setting dropdown. 7. Select the "Details" option. | C108: The calendar view should display appointments based on the "Details" status. | E108: Yes | F108: Marcelo | I108: Marcelo
A109: Verify that the user selects the "X (hidden)" option under "Schedule Text" in the calendar setting dropdown. | B109: 1. Launch the OP application. 2. Select the clinical tab in the top-left corner of the window. 3. Click on the Schedule Icon. 4. Choose the "My View" option and click the location dropdown (i.e., the down arrow). 5. Select the primary location. 6. Click on the calendar setting dropdown. 7. Select the "X (hidden)" option. | C109: The calendar view should display appointments based on the "X (hidden)" status. | E109: Yes | F109: Marcelo | I109: Marcelo
A110: Verify that the user selects the "Name Only" option under "Schedule Text" in the calendar setting dropdown. | B110: 1. Launch the OP application. 2. Select the clinical tab in the top-left corner of the window. 3. Click on the Schedule Icon. 4. Choose the "My View" option and click the location dropdown (i.e., the down arrow). 5. Select the primary location. 6. Click on the calendar setting dropdown. 7. Select the "Name Only" option. | C110: The calendar view should display appointments based on the "Name Only" status. | E110: Yes | F110: Marcelo | I110: Marcelo
... A115: Verify that user are able to set the toggle(?) to an appointment to indicate if the appointment has not been confirmed | B115: 1. Launch the application. 2. Enter valid credentials and click the login button. 3. Click the Clinical tab and select the Schedule button. 4. Click on an appointment to select it. 5. With the appointment highlighted, click on the toggle(?) button in the task bar below the calendar to indicate that the appointment has not been confirmed. 6. Ensure that the toggle now displays on the appointment. | C115: The user should be able to set the toggles on the appointment for the patient. | E115: Yes | F115: Marcelo | I115: Marcelo
A116: Schedule an Appointment for an Established Patient
A117: Verify that the user is able to schedule a new appointment for a patient by double-clicking the time slot in the schedule window. | B117: 1. Launch the OP application. 2. Select the clinical tab in the top-left corner of the window. 3. Click the Schedule Icon. 4. Choose the "My View" option and click the location dropdown (i.e., the down arrow). 5. Select the primary location. 6. Choose a time slot and double-click the slot. 7. The "Add/Edit Appointment" window is displayed. Search for the patient in the search box and click the search icon. 8. Patient information is listed in the respective dropdowns. 9. Fill in the required fields such as Appointment reason and type. 10. Click the "Save" button. | C117: The new appointment should appear in the scheduled time slot. | E117: Yes | F117: Walter | I117: Walter
A118: Verify that the user is able to schedule a new appointment for a patient by right-clicking on the time slot and selecting the "Add Appointment" option in the schedule window. | B118: 1. Launch the OP application. 2. Select the clinical tab in the top-left corner of the window. 3. Click the Schedule Icon. 4. Choose the "My View" option and click the location dropdown (i.e., the down arrow). 5. Select the primary location. 6. Choose a time slot, then right-click on the time slot and select the "Add Appointment" option. 7. The "Add/Edit Appointment" window is displayed. Search for the patient in the search box and click the search icon. 8. Patient information is listed in the respective dropdowns. 9. Fill in the required fields such as Appointment reason and type. 10. Click the "Save" button. | C118: The new appointment should appear in the scheduled time slot. | E118: Yes | F118: Walter | I118: Walter
A119: Verify that the user is able to schedule a new appointment for a patient by clicking on the time slot and selecting the "Add" button in the schedule window. | B119: 1. Launch the OP application. 2. Select the clinical tab in the top-left corner of the window. 3. Click the Schedule Icon. 4. Choose the "My View" option and click the location dropdown (i.e., the down arrow). 5. Select the primary location. 6. Choose a time slot, then click on the time slot and select the "Add" button on the right side of the window. 7. The "Add/Edit Appointment" window is displayed. Search for the patient in the search box and click the search icon. 8. Patient information is listed in the respective dropdowns. 9. Fill in the required fields such as Appointment reason and type. 10. Click the "Save" button. | C119: The new appointment should appear in the scheduled time slot. | E119: Yes | F119: Walter | I119: Walter
A120: Check if the staff can search for the patient using the last name, first name, ID, or phone number of the patient in the Add/Edit Appointments window. | B120: 1. Launch the OP application. 2. Select the clinical tab in the top-left corner of the window. 3. Click the Schedule Icon. 4. Choose the "My View" option and click the location dropdown (i.e., the down arrow). 5. Select the primary location. 6. Choose a time slot, then click on the time slot and select the "Add" button on the right side of the window. 7. The "Add/Edit Appointment" window is displayed. Search for the patient in the search box using the last name, first name, ID, or phone number of the patient. | C120: The user should be able to successfully search for the patient using the last name and first name in the Add/Edit Appointment window. | E120: Yes | F120: Walter | I120: Walter
A121: Verify that the patient details such as Name, Date of Birth, Gender, and Age values are auto-populated when searching and selecting the patient from the Add/Edit Appointment window. | B121: 1. Launch the OP application. 2. Select the clinical tab in the top-left corner of the window. 3. Click the Schedule Icon. 4. Choose the "My View" option and click the location dropdown (i.e., the down arrow). 5. Select the primary location. 6. Choose a time slot, then click on the time slot and select the "Add" button on the right side of the window. 7. The "Add/Edit Appointment" window is displayed. Search for the patient in the search box and select the patient. 8. Ensure that the patient details are auto-populated in the Add/Edit Appointment window. | C121: Patient details should be "Auto Populated" after searching for the patient in the Add/Edit Appointment window. | E121: Yes | F121: Walter | I121: Walter
A122: Verify that the patient's insurance information is displayed in the Add/Edit Appointment window. | B122: 1. Launch the OP application. 2. Select the clinical tab in the top-left corner of the window. 3. Click the Schedule Icon. 4. Choose the "My View" option and click the location dropdown (i.e., the down arrow). 5. Select the primary location. 6. Choose a time slot, then click on the time slot and select the "Add" button on the right side of the window. 7. The "Add/Edit Appointment" window is displayed. Search for the patient in the search box and select the patient. 8. Ensure that the insurance details are listed for the patient. | C122: Patient insurance details should be "Auto Populated" after searching for the patient in the Add/Edit Appointment window. | E122: Yes | F122: Walter | I122: Walter
A123: Verify that the staff can validate the insurance from the Add/Edit Appointments window. | B123: 1. Launch the OP application. 2. Select the clinical tab in the top-left corner of the window. 3. Click the Schedule Icon. 4. Choose the "My View" option and click the location dropdown (i.e., the down arrow). 5. Select the primary location. 6. Choose a time slot, then click on the time slot and select the "Add" button on the right side of the window. 7. The "Add/Edit Appointment" window is displayed. Search for the patient in the search box and select the patient. 8. Ensure that the staff can validate the insurance by clicking on the "Validate" button in the primary insurance section. | C123: The user should validate the insurance in the Add/Edit Appointment window. Note: If the patient does not have insurance, a popup will appear stating "No Patient Selected". | E123: Yes | F123: Walter | I123: Walter
A124: Verify that the user is able to modify the appointment for the patient. | B124: 1. Launch the application. 2. Enter valid credentials and click the login button. 3. Click on any of the tabs such as Clinical, Billing, or Practice Management and access the Schedule button. 4. Click on the "Calendar" radio button to access the appointment schedule window. 5. Double-click on the time slot to add a new/edit appointment. 6. Use the Search box to find the patient and select an Appointment Reason and Appointment Type from the dropdown menus. 7. Click the "Save" button. | C124: The user should be able to modify appointments. | E124: Yes | F124: Walter | I124: Walter
A125: Verify that the user can add appointments in a future date by choosing a date from the calendar view. | B125: 1. Launch the OP application. 2. Select the clinical tab in the top-left corner of the window. 3. Click the Schedule Icon. 4. Choose the "My View" option and click the location dropdown (i.e., the down arrow). 5. Select the primary location. 6. Choose a future date from the calendar. 7. Choose a time slot, then double-click on the slot. 8. The "Add/Edit Appointment" window is displayed. Search for the patient in the search box and click the search icon. 9. Patient information is listed in the respective dropdowns. 10. Fill in the required fields such as Appointment reason and type. 11. Click the "Save" button. | C125: The new appointment should appear in the future scheduled time slot. | D125: SalesForce | E125: Yes | F125: Walter | I125: Walter
A126: Verify that the user can choose a date other than today on the calendar page, and the chosen date remains selected after clicking on the tracking page. | B126: 1. Launch the OP application. 2. Select the clinical tab in the top-left corner of the window. 3. Click the Schedule Icon and navigate to the Calendar tab. 4. Choose a date other than today. 5. Click on the Tracking tab, and verify that the chosen date remains selected from the schedule page. | C126: Choose a date from the calendar view, then clicking on the tracking tab should automatically change to the selected date without requiring another manual change. | D126: SalesForce | I126: Bruno
A127: Verify that accidental deletion and moving of appointments does not occur when the user double right-clicks on the existing appointment. | B127: 1. Log into OP with valid credentials. 2. Navigate to Clinical -> Schedule. 3. Left-click on an existing appointment in the schedule window to select it. 4. Then right-click on the same appointment to get the menu selection to appear. 5. Right-click again on one of the options to select it. 6. Ensure that a user cannot accidentally print reports, delete appointments, or move appointments when right-clicking on the appointment twice. | C127: Any accidental deletion and moving of appointments should not occur when the user double right-clicks on the existing appointment. | D127: SalesForce | I127: Bruno
A128: Verify that the appointment is not deleted or moved when the user opens the encounter note from the schedule. | B128: 1. Log into the OP application with valid credentials. 2. Select the clinical tab in the top-left corner of the window. 3. Click the Schedule Icon. 4. Create an appointment. 5. Select the appointment and right-click on it, then click on the "Open Encounter" option from the menu. 6. Create a new note or do not navigate back to the schedule page. 7. Check that the appointment is not deleted or moved. | C128: The appointment should not be deleted or moved when the user opens the encounter note from the schedule. | D128: SalesForce | I128: Bruno
A129: Verify that the appointment is not deleted or moved when the user opens the well visit note from the schedule. | B129: 1. Log into the OP application with valid credentials. 2. Select the clinical tab in the top-left corner of the window. 3. Click the Schedule Icon. 4. Create an appointment. 5. Select the appointment and right-click on it, then click on the "Open Well Visit" option from the menu. 6. Create a new note or do not navigate back to the schedule page. 7. Check that the appointment is not deleted or moved. | C129: The appointment should not be deleted or moved when the user opens the well visit note from the schedule. | D129: SalesForce | I129: Bruno
A130: Verify that the free-typed information from the Appointment Reason field is visible in the CC line of the note. | B130: 1. Launch the OP application. 2. Select the clinical tab in the top-left corner of the window. 3. Click the Schedule Icon. 4. Select the "My View" option and click the location dropdown (i.e., the down arrow). 5. Choose the primary location. 6. Choose a time slot and double-click on the slot. 7. The "Add/Edit Appointment" window is displayed. Search for the patient in the search box and click the search icon. 8. Patient information is listed in the respective dropdowns. 9. Enter a custom appointment reason in the respective field and select an appointment type. 10. Click the "Save" button. 11. Select the appointment, then right-click on it and click the "Open Encounter" option from the menu. 12. In the CC field of the encounter note, verify that the custom appointment reason you entered while adding the appointment is displayed. 13. Navigate to the summary tab of the encounter note and verify that the custom appointment reason you entered is displayed under the CC/HPI header. | C130: Free-typed information from the Appointment Reason field should be visible in the CC line of the note. | D130: RelaseFilter | E130: Yes | F130: Walter | I130: Walter
A131: Verify that the user does not receive any Access Violation error when clicking the save button on the Add/Edit Appointment window under the schedule page. | B131: 1. Log into the OP with valid credentials. 2. Click the Clinical tab. 3. Click the Schedule icon to navigate to the calendar window. 4. Select the time slot, then right-click. 5. Click "Add Appointment". 6. Ensure that the appointment window opens. 7. Select the patient using the patient finder. 8. Fill in the required fields. 9. Click the "Save" button. 10. Verify that the user does not receive any Access Violation error. | C131: The user should not receive an Access Violation error when scheduling the appointment for a patient on the calendar window. | D131: Filter | I131: Bruno
A132: Register a New patient
A133: Verify that the user is able to access the new patient page. | B133: 1. Launch the application. 2. Enter valid credentials and click the login button. 3. Click on any of the tabs such as Clinical, Billing, or Practice Management and access the Patient Chart button. 4. Click on the Patient Finder button. 5. Click on the New Patient button. | C133: The new patient page should be accessible. | E133: Yes | F133: Marcelo | I133: Marcelo
A134: Verify that the user is able to add a new patient in the application. | B134: 1. Launch the application. 2. Enter valid credentials and click the login button. 3. Click on any of the tabs such as Clinical, Billing, or Practice Management and access the Patient Chart button. 4. Click on the Patient Finder button. If the patient is not listed in your search, 5. Click the New Patient button and add a new patient in the application. | C134: The new patient should be added successfully in the application. | E134: Yes | F134: Marcelo | I134: Marcelo
A135: Verify that when the user edits the ZIP code, the City field gets updated accordingly. | B135: 1. Log in to the OP. 2. Navigate to Patient Chart and search for a patient. 3. Navigate to Basic Information. 4. Edit the ZIP code, and verify that the City is not getting updated. | C135: The user should view the City getting updated when editing the ZIP code. | D135: Exploratory | I135: Marcelo
A136: Verify that the user is able to merge a patient in the application. | B136: 1. Launch the application. 2. Enter valid credentials and click the login button. 3. Click on any of the tabs such as Clinical, Billing, or Practice Management and access the Patient Chart button. 4. Click on the Patient Finder button. If the patient is listed in your search, 5. Select the patient. Within the Patient Chart, click on Basic Information. 6. Click the Merge button, and a Confirmation pop-up box is displayed. Review the information. 7. Click the "Yes" button. 8. Search for and select the Patient whose chart the records should be merged into. 9. Click the "Select" button and confirm the merge. 10. Once the merge is complete: - The status of the merged Patient Chart will be changed to "Merged." - "XXX" is displayed in front of the patient's name. | C136: The user should be able to merge the duplicate patient chart details. | E136: Yes | F136: Marcelo | I136: Marcelo
A137: Verify that the user is able to add a new patient with only the required fields: - Last Name - First Name - Birth Date - Sex - Primary Address - Primary Phone - Primary Provider | B137: 1. Launch the application. 2. Enter valid credentials and click the login button. 3. Click on any of the tabs such as Clinical, Billing, or Practice Management and access the Patient Chart button. 4. Click on the Patient Finder button. If the patient is not listed in your search, 5. Click the New Patient button and add a new patient with only the required fields. | C137: The new patient with the required fields should be added successfully in the application. | E137: Yes | F137: Marcelo | I137: Marcelo
A138: Verify that a required error popup is displayed if the user adds a new patient without the following fields: "Last Name, First Name, Birth Date, Sex, Primary Address, Primary Phone, Primary Provider". | B138: 1. Launch the application. 2. Enter valid credentials and click the login button. 3. Click on any of the tabs such as Clinical, Billing, or Practice Management and access the Patient Chart button. 4. Click on the Patient Finder button. If the patient is not listed in your search, 5. Click the New Patient button. 6. Try to save the new patient without entering the Last Name, First Name, Birth Date, Sex, Primary Address, Primary Phone, or Primary Provider. 7. Observe the error popup appearing prompting to enter the required fields. | C138: The required error popup should appear when the user saves a new patient without entering the required fields. | D138: Exploratory | E138: Yes | F138: Marcelo | I138: Marcelo
A139: Verify that the user is able to add a new patient with both required and optional fields: Required Fields: - Last Name - First Name - Birth Date - Sex - Primary Address - Primary Phone - Primary Provider Optional Fields: - Middle Name - Gender Identity - Orientation - Language - Country - Cell Phone - Email Address - Emergency Contact - VFC Eligibility - Medical Home - Team - Risk Group - Alternate ID - Alternate Last Name - Alternate First Name - Ethnicity - Race - Status | B139: 1. Launch the application. 2. Enter valid credentials and click the login button. 3. Click on any of the tabs such as Clinical, Billing, or Practice Management and access the Patient Chart button. 4. Click on the Patient Finder button. If the patient is not listed in your search, 5. Click the New Patient button and add a new patient with both required and optional fields. | C139: The new patient with both required and optional fields should be added successfully in the application. | E139: Yes | F139: Marcelo | I139: Marcelo
A140: Verify that the user is able to search for the newly added patient in the application. | B140: 1. Launch the application. 2. Enter valid credentials and click the login button. 3. Click on any of the tabs such as Clinical, Billing, or Practice Management and access the Patient Chart button. 4. Click on the Patient Finder button and search for the newly added patient. 5. Verify that the newly added patients are listed in your search results. | C140: The new patient should be listed in your search results. | E140: Yes | F140: Marcelo | I140: Marcelo
A141: Verify that the dropdown option is removed from the language field. | B141: 1. Log into OP. 2. Open a patient's chart. 3. Navigate to the Basic Info tab. Note: Ensure that the dropdown for language has been removed in both fields. | C141: The dropdown option should be removed from the language field. | D141: Insprint | I141: Bruno
...

Sheet Billing
A1: TEST SCENARIO | B1: STEPS | C1: EXPECTED RESULTS | D1: HighLevel | E1: Owner - FB(High level) | F1: Status | G1: Comment | H1: Owner - MySQL(Full regression) | I1: Status | J1: Comment
A2: Billing - Setup
A3: Verify user able to access the Diagnosis code management window. | B3: 1.Launching the application 2.Enter the valid credential and click login button 3.Click the anyone of tab clinical, billing and access the Diagnosis code button 4.Make sure the diagnosis management window is getting popped up. | C3: Diagnosis Management window should popped up while clicks on Diagnosis code in billing tab. | D3: Yes | E3: Gustavo | H3: Gustavo
A4: Verify user able to add new diagnosis code | B4: 1.Launching the application 2.Enter the valid credential and click login button 3.Click the anyone of tab clinical, billing and access the Diagnosis code button 4.Access the diagnosis management window opened 5.Click the New button and The Diagnostic Code Editor window is displayed. 6.Enter the information and save the new diagnosis. | C4: New diagnosis code should be added. | D4: Yes | E4: Gustavo | H4: Gustavo
A5: Verify user able to edit the diagnosis code | B5: 1.Launching the application 2.Enter the valid credential and click login button 3.Click the anyone of tab clinical, billing and access the Diagnosis code button 4.Access the diagnosis management window opened 5.Search for the Diagnosis code to edit. 6.Click to select the Diagnosis Code. 7.Click the Edit button. 8.Edit the Diagnosis code using the table descriptions above. 9.Click the Save button. | C5: Diagnosis code should be edited | D5: Yes | E5: Gustavo | H5: Gustavo
A6: Verify the error popup will shown while adding a new diagnosis code without code set value | B6: 1.Launching the application 2.Enter the valid credential and click login button 3.Click the anyone of tab clinical, billing and access the Diagnosis code button 4.Access the diagnosis management window opened 5.Click the New button and The Diagnostic Code Editor window is displayed. 6.Add a diagnosis code without code set value. 7.Click on Save button. 8."Code set is a required field" error popup should appear. | C6: "Code set is a required field" error popup should be displayed while adding a new diagnosis code without code set value | D6: Yes | E6: Gustavo | H6: Gustavo
A7: Verify the opened diagnostic code editor window is closed after clicking the cancel button | B7: 1.Launching the application 2.Enter the valid credential and click login button 3.Click the anyone of tab clinical, billing and access the Diagnosis code button 4.Access the diagnosis management window opened 5.Click the New button and access the Diagnostic Code Editor window opened 6.Click on Cancel button | C7: Opened window should be closed after clicking the cancel button | D7: Yes | E7: Gustavo | H7: Gustavo
A8: Verify user able to search the diagnosis code by clicking any alphabets at the bottom of the page | B8: 1.Launching the application 2.Enter the valid credential and click login button 3.Click the anyone of tab clinical, billing and access the Diagnosis code button 4.Access the diagnosis management window opened 5.Select the "Complete" radio button and click any one alphabets at the bottom of the page. 6.verify the searched alphabet diagnosis codes are listed in your search | C8: Searched diagnosis code should be displayed | D8: Yes | E8: Gustavo | H8: Gustavo
A9: Verify user able to search the diagnosis code with below option Search for the diagnosis code to map: Enter the search criteria (Code or Description). Select the correct Result Set radio button. Click the Search button. | B9: 1.Launching the application 2.Enter the valid credential and click login button 3.Click the anyone of tab clinical, billing and access the Diagnosis code button 4.Access the diagnosis management window opened 5.Search for the Diagnosis code and verify the searched diagnosis are listed in your search | C9: Searched diagnosis code should be displayed | D9: Yes | E9: Gustavo | H9: Gustavo
A10: Verify user able to print the diagnosis code | B10: 1.Launching the application 2.Enter the valid credential and click login button 3.Click the anyone of tab clinical, billing and access the Diagnosis code button 4.Access the diagnosis management window opened 5.Search for the Diagnosis code to print or click any alphabet letters at the bottom of the page. 6.Click on print button. | C10: Diagnosis code should be displayed in print preview page. | D10: Yes | E10: Gustavo | H10: Gustavo
A11: Verify user can ordering the diagnosis code by using sort number | B11: 1.Launching the application 2.Enter the valid credential and click login button 3.Click the anyone of tab clinical, billing and access the Diagnosis code button 4.Access the diagnosis management window opened 5.Select the "Complete" radio button and click any one alphabets at the bottom of the page. 6.Select the first Diagnosis Code which are listed. 7.Click the Edit button. 8.Click the Sort Order field and edit the sort number by using dropdown values or manually entering the data. 9.Click the Save button. 10.Check whether the selected diagnosis code is listed by sortnumber. | C11: Diagnosis code should be listed by sort number | D11: Yes | E11: Gustavo | H11: Gustavo
A12: Verify user able to Editing a sort number for exist diagnosis code | B12: 1. Launching the application 2. enter the valid credential and click login button 3. Click the billing tab and access the diagnosis code button 4. Access the diagnosis codes window 5. Search for diagnosis codes in search field and select the diagnosis codes 6. Click the Edit button and edit the sort number in sort field. 7. click the save button | C12: Sort number should be edited for diagnosis codes | D12: Yes | E12: Gustavo | H12: Gustavo
A13: Verify user able to Deleting a Sort number for exist diagnosis code | B13: 1. Launching the application 2. enter the valid credential and click login button 3. Click the billing tab and access the diagnosis code button 4. access the diagnosis codes window 5. Search for diagnosis codes in search field and select the diagnosis codes 6. Click the Edit button and click in the sortfield and delete the text of the sort that you do not want. 7. click the save button | C13: Sort number should be deleted for diagnosis codes | D13: Yes | E13: Gustavo | H13: Gustavo
A14: Verify user able to add new category for diagnosis code | B14: 1.Launching the application 2.Enter the valid credential and click login button 3.Click the anyone of tab clinical, billing and access the Diagnosis code button 4.Access the diagnosis management window opened 5.Search for the Diagnosis code to edit. 6.Click to select the Diagnosis Code. 7.Click the Edit button. 8.Click on Category field and clear the category name. 9.Type the new category name in the Category field 10.Click on Save button. 11.Click on yes button in confirm popup window. 12.Check whether the Category field should be edited for searched diagnosis code 13.Click the Edit button. 14.Click on Category field dropdown. 15.Check whether the newly created category name is listed in Category field dropdown and You will now be able to search for this code under the category. | C14: Newly created category name should be listed in Category field dropdown | D14: Yes | E14: Gustavo | H14: Gustavo
... A16: Verify user able to assigning the synonym for the diagnosis code | B16: 1. Launching the application 2. Enter the valid credential and click login button 3. Click the anyone of tab clinical, billing and access the Diagnosis code button 4. Access the diagnosis management window opened. 5. Search for the Diagnosis code and verify the searched diagnosis are listed in your search 6. Select the searched diagnosis and click the edit button 7. Diagnosis code edit window will open and select synonym tab 8. Click the Insert record button at the bottom of the window to add a new synonym. Once added, click the green check mark to save. 9. You will now be able to search for this code under the synonym. | C16: New synonym should be added for diagnosis code and User should be searched the diagnosis code using it's synonym | D16: Yes | E16: Gustavo | H16: Gustavo
A17: Verify user able to edit the synonym for the diagnosis code | B17: 1. Launching the application 2. Enter the valid credential and click the login button 3. Click the anyone of tab clinical, billing and access the Diagnosis code button 4. Access the diagnosis management window opened. 5. Search for the Diagnosis code and verify the searched diagnosis are listed in your search 6. Select the searched diagnosis and click the edit button 7. Diagnosis code edit window will open and select the synonym tab 8. Select the synonym which you want to edit. 9. Click the Edit icon at the bottom of the window and edit that. 10. Once edited, click the green check mark to save. 11. check whether the selected synonym is edited in the synonyms tab. | C17: Selected synonym should be edited | H17: Gustavo
A18: Verify user able to delete the synonym for the diagnosis code | B18: 1. Launching the application 2. Enter the valid credential and click login button 3. Click the anyone of tab clinical, billing and access the Diagnosis code button 4. Access the diagnosis management window opened. 5. Search for the Diagnosis code and verify the searched diagnosis are listed in your search 6. Select the searched diagnosis and click the edit button 7. Diagnosis code edit window will open and select synonym tab 8. Select the synonym which you want to delete. 9. Click the delete icon at the bottom of the window. 10.Click on ok button in confirm popup window. 11.check whether the selected synonym is not displayed in synonyms tab. | C18: Selected synonym should be deleted | D18: Yes | E18: Gustavo | H18: Gustavo
A19: Verify user able to assigning the groups of diagnosis code | B19: 1.Launching the application 2.Enter the valid credential and click login button 3.Click the anyone of tab clinical, billing and access the 1. Launching the application 2. Enter the valid credential and click login button 3. Click the anyone of tab clinical, billing and access the Diagnosis code button 4. Access the diagnosis management window opened. 5. Search for the Diagnosis code and verify the searched diagnosis are listed in your search 6. Select the searched diagnosis and click the edit button 7. Diagnosis code edit window will open and select the synonym tab 8. Select the synonym which you want to edit. 9. Click the Edit icon at the bottom of the window and edit that. 10.Once edited, click the green check mark to save. 11.check whether the selected synonym is edited in synonyms tab. code button 4.Access the diagonsis management window opened. 5.Search for the Diagnosis code and verify the searched diagnosis are listed in your search 6.Select the searched diagnosis and click the edit button 7.Diagnosis code edit window will open and select Diagnostic group tab 8.Click the Insert record button at the bottom of the window to add a new Diagnostic Group. Once added, click the green check mark to save. 9.You will now be able to search for this code under the diagnostic group. | C19: New diagnostic group should be added | D19: Yes | E19: Gustavo | H19: Gustavo
A20: Verify user able to edit the group for the diagnosis code | B20: 1. Launching the application 2. Enter the valid credential and click login button 3. Click the anyone of tab clinical, billing and access the Diagonsis code button 4. Access the diagonsis management window opened. 5. Search for the Diagnosis code and verify the searched diagnosis are listed in your search 6. Select the searched diagnosis and click the edit button 7. Diagnosis code edit window will open and select Diagnostic groups tab 8. Select the goup which you want to edit. 9. Click the Edit icon at the bottom of the window and edit that. 10.Once edited, click the green check mark to save. 11.check whether the selected group is edited in diagnostic groups tab | C20: Selected group should be edited | H20: Gustavo
A21: Verify user able to delete the group for the diagnosis code | B21: 1. Launching the application 2. Enter the valid credential and click login button 3. Click the anyone of tab clinical, billing and access the Diagonsis code button 4. Access the diagonsis management window opened. 5. Search for the Diagnosis code and verify the searched diagnosis are listed in your search 6. Select the searched diagnosis and click the edit button 7. Diagnosis code edit window will open and select diagnostic groups tab 8. Select the group which you want to delete in diagnostic groups tab tab. 9. Click the delete icon at the bottom of the window. 10.Click on ok button in confirm popup window. 11.check whether the selected group is not displayed in Diagnostic groups tab. | C21: Selected group should be deleted | D21: Yes | E21: Gustavo | H21: Gustavo
A22: Verify user able to assign the "cross mappings" for diagnosis code. | B22: 1.Launching the application 2.Enter the valid credential and click login button 3.Click the anyone of tab clinical, billing and access the Diagonsis code button 4.Access the diagonsis management window opened. 5.Search for the Diagnosis code and verify the searched diagnosis are listed in your search 6.Select the searched diagnosis and click the edit button 7.Diagnosis code edit window will open and select the cross mappings tab 8.Click the Insert record button at the bottom of the window to add a new cross mappings. 9.Click the dropdown of mapped diagnosis field, the diagonsis management window is getting poped up 10.Enter the dx code in search field and click on search button. 11.Once added, click the green check mark to save. 12.check whether the newly created cross mappings is added in cross mappings tab | C22: New cross Mappings should be added. | D22: Yes | E22: Gustavo | H22: Gustavo
A23: Verify user able to edit the "cross mappings" for diagnosis code. | B23: 1. Launching the application 2. Enter the valid credential and click login button 3. Click the anyone of tab clinical, billing and access the Diagonsis code button 4. Access the diagonsis management window opened. 5. Search for the Diagnosis code and verify the searched diagnosis are listed in your search 6. Select the searched diagnosis and click the edit button 7. Diagnosis code edit window will open and select cross mappings tab 8. Select the cross mappings which you want to edit. 9. Click the Edit icon at the bottom of the window and edit that. 10.Once edited, click the green check mark to save. 11.check whether the selected cross mappings is edited in cross mappings tab | C23: Selected Cross Mappings should be edited | H23: Gustavo
A24: Verify user able to delete the "cross mappings" for diagnosis code. | B24: 1. Launching the application 2. Enter the valid credential and click login button 3. Click the anyone of tab clinical, billing and access the Diagonsis code button 4. Access the diagonsis management window opened. 5. Search for the Diagnosis code and verify the searched diagnosis are listed in your search 6. Select the searched diagnosis and click the edit button 7. Diagnosis code edit window will open and select cross mappings tab 8. Select the cross mappings which you want to delete 9. Click the delete icon at the bottom of the window. 10.Click on ok button in confirm popup window. 11.check whether the selected cross mappings is not displayed in cross mappings tab. | C24: Selected Cross Mappings should be deleted | D24: Yes | E24: Gustavo | H24: Gustavo
A25: Verify user able to access the CPT code management | B25: 1.Launching the application 2.enter the valid credential and click login button 3.Click the billing tab and access the procedure CPT code button 4.Check whether the user able to acces the procedure CPT codes window | C25: CPT code should be accessable | D25: Yes | E25: Gustavo | H25: Gustavo
A26: Verify the opened cpt code management window is closed after clicking the cancel button | B26: 1.Launching the application 2.Enter the valid credential and click login button 3.Click the anyone of tab clinical, billing and access the procedure CPT code button 4.Access the procedure CPT codes window opened 5.Click on Cancel button | C26: Opened Cpt code window should be closed after clicking the cancel button | D26: Yes | E26: Gustavo | H26: Gustavo
A27: Verify user able to search the CPT code using below search criteria "Frequently Used,Complete,Category," | B27: 1.Launching the application 2.enter the valid credential and click login button 3.Click the billing tab and access the CPT code button 4.access the CPT codes window 5.Search for the CPT code using search option and verify the searched CPT are listed in your search | C27: User can search the CPT code using search criteria. | D27: Yes | E27: Gustavo | H27: Gustavo
A28: Verify user able to add new CPT code | B28: 1.Launching the application 2.enter the valid credential and click login button 3.Click the billing tab and access the CPT code button 4.access the CPT codes window 5.Click edit button,The CPT-4: Physicians Current Procedural Terminology window opens. 6.Click the Add button enter the information 7.Click save button | C28: New CPT code should be added. | D28: Yes | E28: Gustavo | H28: Gustavo
A29: Verify user able to Edit CPT code | B29: 1.Launching the application 2.enter the valid credential and click login button 3.Click the billing tab and access the CPT code button 4.access the CPT codes window 5.Search for CPT codes in search box and select the CPT code you would like to edit. 6.Click the Edit button and make an necessary changes(description) 7.Click save button | C29: User can modify the CPT codes | D29: Yes | E29: Gustavo | H29: Gustavo
A30: Verify user able to Delete CPT code | B30: 1.Launching the application 2.enter the valid credential and click login button 3.Click the billing tab and access the CPT code button 4.access the CPT codes window 5.Search for CPT codes in search box and select the CPT code you would like to delete. 6.Click the delete button and click yes button to confirm 7.verify the cpt codes is deleted | C30: User can Delete the CPT codes | D30: Yes | E30: Gustavo | H30: Gustavo
A31: Verify that the user is not viewing '21310' and '33470' Delete the CPT code in the CPT codes window | B31: 1. Launching the application 2. Enter the valid credential and click the login button 3. Click the billing tab and access the CPT code button 4. Access the CPT codes window 5. Search for '21310' and '33470' Delete the CPT code in the search box Note: Ensure delete CPT code is not visible in the CPT codes window | C31: User ensure '21310' and '33470' Delete CPT code not visible in CPT codes window | H31: Gustavo
A32: Verify user able to view the fee schedule for the individual cpt codes | B32: 1.Launching the application 2.enter the valid credential and click login button 3.Click the billing tab and access the CPT code button 4.access the CPT codes window 5.Search for CPT codes in search box and select the cpt codes 6.view the fee schedule for the cpt codes | C32: User can view the CPT code fee schedule | D32: Yes | E32: Gustavo | H32: Gustavo
A33: Verify user able to edit the fee schedule for the individual cpt codes | B33: 1. Launching the application 2. enter the valid credential and click login button 3. Click the billing tab and access the CPT code button 4. access the CPT codes window 5. Search for CPT codes in search box and select the cpt codes 6. click in the appropriate Fee field and make your edits. 7. click the save button | C33: User can edit the CPT code fee schedule | D33: Yes | E33: Gustavo | H33: Gustavo
A34: Verify user able to copy the fee schedules for the individual cpt codes | B34: 1. Launching the application 2. enter the valid credential and click login button 3. Click the billing tab and access the CPT code button 4. access the CPT codes window 5. Search for CPT codes in search box and select the cpt codes 6. Click the Modify Fee Schedule button. 7. Fill out the equation as needed. 8. click Apply to save your changes. 9. Click Done to close the window.You will have to close the CPT code table and reopen it to see the changes. | C34: User can copy one fee schedules to another fee schedules | H34: Gustavo
A35: Verify user able to add new category for the CPT code | B35: 1. Launching the application 2. enter the valid credential and click login button 3. Click the billing tab and access the CPT code button 4. access the CPT codes window 5. Click edit button,The CPT-4: Physicians Current Procedural Terminology window opens. 6. Click the Edit button to edit the CPT Code. 7. Click in the Category field and Type the new Category name 8. Click the Save button. The new category will now be visible in the Category drop-down list when searching for CPT codes. | C35: User can add a new category | D35: Yes | E35: Gustavo | H35: Gustavo
A36: Verify user able to adding a category for exist CPT code | B36: 1. Launching the application 2. enter the valid credential and click login button 3. Click the billing tab and access the CPT code button 4. access the CPT codes window 5. Search for CPT codes in search box and select the cpt codes 6. Click the Edit button and Click the Category drop-down and select the appropriate category. 7. click the save button | C36: User can add a new category for the exist cpt codes | D36: Yes | E36: Gustavo | H36: Gustavo
A37: Verify user able to Editing a category for exist CPT code | B37: 1. Launching the application 2. enter the valid credential and click login button 3. Click the billing tab and access the CPT code button 4. access the CPT codes window 5. Search for CPT codes in search box and select the cpt codes 6. Click the Edit button and Click the Category drop-down and select the appropriate category. 7. click the save button | C37: User can edit a category | H37: Gustavo
A38: Verify user able to Deleting a category for exist CPT code | B38: 1. Launching the application 2. enter the valid credential and click login button 3. Click the billing tab and access the CPT code button 4. access the CPT codes window 5. Search for CPT codes in search box and select the cpt codes 6. Click the Edit button and click in the Category field and delete the text of the category that you do not want. 7. click the save button | C38: User can Delete a category | D38: Yes | E38: Gustavo | H38: Gustavo
A39: Verify user able to adding a sort number for exist CPT code | B39: 1. Launching the application 2. enter the valid credential and click login button 3. Click the billing tab and access the CPT code button 4. access the CPT codes window 5. Search for CPT codes in search box and select the cpt codes 6. Click the Edit button and Click the sort field and adding the sort 7. click the save button | C39: Sort number should be added for CPT codes | D39: Yes | E39: Gustavo | H39: Gustavo
A40: Verify user able to Editing a sort for exist CPT code | B40: 1. Launching the application 2. enter the valid credential and click login button 3. Click the billing tab and access the CPT code button 4. access the CPT codes window 5. Search for CPT codes in search box and select the cpt codes 6. Click the Edit button and edit the sort number in sort field. 7. click the save button | C40: Sort number should be edited for CPT codes | D40: Yes | E40: Gustavo | H40: Gustavo
A41: Verify the below mentioned CPT code is in the Complete List of the CPT code table i) 91304, ii) 0041A and iii) 0042A | B41: 1.Launching the application 2.Enter the valid credential and click login button 3.Click the billing tab and access the CPT code button 4.Access the CPT codes window 5.Select the "Complete List" radio button 6.Type the mentioned CPT code in search field and click "Search" button 7.Verify the mentioned CPT code are listed in the Complete List of the CPT code table | C41: Mentioned CPT code should be in the Complete List of the CPT code table | H41: Gustavo
A42: Verify the 91304 and 0041A cpt code charges are added in the unposted charges window after adding the first dose - "Novax vaccine" from the inventory tab | B42: 1. Launching the application 2. Enter the valid credential and click login button 3. Choose one patient from patient chart and Navigate to Immunizations > Administer Vaccine 4. Select and add the"Covid 19 30" from the inventory 5. In the Enter vaccine Administration Information window enter body site and make sure Add vaccine to superbill box is checked 6. Click on Save button 7. Navigate to Charges tab 8. Verify the 91304 and 0041A claim is added in the unposted charges window | C42: 91304 and 0041A claim is added in the unposted charges window | H42: Gustavo
A43: Verify the 91304 and 0042A cpt code charges are added in the unposted charges window after adding the second dose - "Novax vaccine" from the inventory tab | B43: 1. Launching the application 2. Enter the valid credential and click login button 3. Choose one patient from patient chart and Navigate to Immunizations > Administer Vaccine 4. Select and add the"Covid 19 30" from the inventory 5. In the Enter vaccine Administration Information window enter body site and make sure Add vaccine to superbill box is checked 6. Click on Save button 7. Navigate to Charges tab 8. Verify the 91304 and 0042A claim is added in the unposted charges window | C43: 91304 and 0042A claim is added in the unposted charges window | H43: Gustavo
A44: Verify user able to Deleting a Sort number for exist CPT code | B44: 1. Launching the application 2. enter the valid credential and click login button 3. Click the billing tab and access the CPT code button 4. access the CPT codes window 5. Search for CPT codes in search box and select the cpt codes 6. Click the Edit button and click in the sortfield and delete the text of the sort that you do not want. 7. click the save button | C44: Sort number should be deleted for CPT codes | H44: Gustavo
A45: Verify user able to print the CPT code | B45: 1.Launching the application 2.Enter the valid credential and click login button 3.Click the anyone of tab clinical, billing and access the CPT code button 4.Access the CPT code window opened 5.Search for the cpt code to print or select the "complete" radio button click any alphabet letters at the bottom of the page. 6.Click on print button. | C45: cpt code should be displayed in print preview page. | D45: Yes | E45: Gustavo | H45: Gustavo
A46: Verify user able to access the "Contracts for CPT" window. | B46: 1.Launching the application 2.Enter the valid credential and click login button 3.Click the anyone of tab clinical, billing and access the CPT code button 4.Access the CPT code window opened 5.Click on Contracts button. 6.Access the Contracts for CPT code window opened | C46: User can access the Contracts for CPT window | D46: Yes | E46: Gustavo | H46: Gustavo
A47: Verify user can view the cpt code contracts | B47: 1.Launching the application 2.Enter the valid credential and click login button 3.Click the anyone of tab clinical, billing and access the CPT code button 4.Access the CPT code window opened 5.Search for the cpt code to view its contracts or click any alphabet letters at the bottom of the page. 6.Click on Contracts button. 7.Access the Contracts for CPT code window opened 8.Check whether the cpt code contracts are listed in Contracts for CPT page. | C47: User can view the cpt code contracts in Contracts for CPT page | H47: Gustavo
A48: Verify user can print the cpt code contracts | B48: 1.Launching the application 2.Enter the valid credential and click login button 3.Click the anyone of tab clinical, billing and access the CPT code button 4.Access the CPT code window opened 5.Search for the cpt code to view its contracts or click any alphabet letters at the bottom of the page. 6.Click on Contracts button. 7.Access the Contracts for CPT code window opened 8.Check whether the respective cpt code contracts are listed in Contracts for CPT page. 9.Click on Print Icon. | C48: Cpt code Contracts should be displayed in print preview page. | D48: Yes | E48: Gustavo | H48: Gustavo
A49: Verify user able to access the insurance payer window | B49: 1. Launching the application 2. enter the valid credential and click login button 3. Click the billing tab and access the Payer button 4. Access the insurance payer window. | C49: Insurance payer should be accessable | D49: Yes | E49: Gustavo | H49: Gustavo
A50: Verify user able to access the insurance payer detail window | B50: 1.Launching the application 2.Enter the valid credential and click login button 3.Click the billing tab and access the Payers button. 4.Access the payers window opened 5.Add the new payer name by clicking New button. 6.Check whether the Insurance payer detail window opened. | C50: Insurance payer detail window should be accessable | D50: Yes | E50: Gustavo | H50: Gustavo
A51: Verify user able to add insurance to the patient | B51: 1.Launching the application. 2.Enter the valid credential and click login button. 3.Navigate to: Billing tab >Patient Chart button > Accounts>Insurance 4.Check whether the Insurance window displays. 5.Click the plus button in Insurance window to add new Insurance for the patient 6.Enter the Insurance details for the patient and save it. 7.Check whether the added Insurance are reflected in Insurance window. | C51: Insurance should be added to the patient | D51: Yes | E51: Gustavo | H51: Gustavo
A52: Verify the modified insurance is displayed in the insurance field of Add/edit charges window | B52: 1.Launching the application. 2.Enter the valid credential and click login button. 3.Navigate to: Billing tab >Patient Chart button > Accounts>Charges 4.Check whether the Charges window displays 5.Click on New superbill button to add superbill for the patient 6.Add Rendering & Supervisor provider, DX code and procedure CPT codes 7.Click on exit button 8.Select the added superbill charges 9.Click the post all button 10.Add/edit charges screen opens 11.Insurance was set to Aetna(Configured insurance) as a default 12.Change this default insurance to Ameriben or any other insurance which you want to modify. 13.Check whether the modified insurance should be displayed in the insurance field of Add/edit charges window | C52: Modified insurance should be displayed in the insurance field of Add/edit charges window | H52: Gustavo
A53: Verify the added insurance is displayed under payer's dropdown in add/edit charges window | B53: 1) Navigate to patient chart and search a patient 2) Navigate to the "Account" tab from navigation panel 3) Click on the "Charges " under accounts tab 4) Click on the "New Superbill" button and add the DX code and procedure codes then exit 5) Highlighted the superbill charges and clicks on "Post All" button 6) Add/edit charges screen opens 7) Check whether the added insurance is displayed or not under payer's dropdown in add/edit charges window | C53: Added insurance should be displayed under payer's dropdown in add/edit charges window | H53: Gustavo
A54: Verify user can able to select the insurance from payers dropdown in add/edit charges window | B54: 1) Navigate to patient chart and search a patient 2) Navigate to the "Account" tab from navigation panel 3) Click on the "Charges " under accounts tab 4) Click on the "New Superbill" button and add the DX code and procedure codes then exit 5) Highlighted the superbill charges and clicks on "Post All" button 6) Add/edit charges screen opens 7) Check whether the added insurance is displayed or not under payer's dropdown in add/edit charges window 8) Select the added insurance from payer dropdown and check whether it is added or not in the payer field | C54: Selected insurance from payers dropdown should be displayed in payer field. | H54: Gustavo
A55: Verify the "hide inactive" checkbox is selected in default | B55: 1. Launching the application 2. enter the valid credential and click login button 3. Click the billing tab and access the Payer button 4. Access the insurance payer window. 5. you can able to see the "hide inactive" checkbox is selected in default. | C55: "hide inactive" checkbox should be selected in default. | D55: Yes | E55: Gustavo | H55: Gustavo
A56: Verify user can able to inactive the insurance payers | B56: 1.Launching the application 2.Enter the valid credential and click login button 3.Click the billing tab and access the Payers button. 4.Access the payers window opened 5.Select one payer and click on edit button. 6.Change the Active status by clicking the "Inactive" radio button. 7.Click the save button. 8.The selected payer is disappeared in payer window. 9.UnSelect the "hide inactive" checkbox, you will now able to see the inactive payer "opcode" field is in red colour. | C56: *User can inactive the insurance payers *Inactive payer "opcode" field should be in red colour. | D56: Yes | E56: Gustavo | H56: Gustavo
A57: Verify user can able to active the inactive insurance payers by using "Active for all" | B57: 1.Launching the application 2.Enter the valid credential and click login button 3.Click the billing tab and access the Payers button. 4.Access the payers window opened 5.UnSelect the "hide inactive" checkbox, you will now able to see the inactive payer "opcode" in red clour. 6.Select one inactive payer and click on edit button. 6.Change the Active status by clicking the "Active for all" radio button. 7.Click the save button. 8.You will now able to see that payer "opcode" field is not in red colour and its in white colour. 9.Select the "hide inactive" checkbox, you will now able to see the payer after selecting "hide inactive" checkbox. | C57: *User can active the inactive insurance payers *Inactive payer "opcode" field should be in white colour | D57: Yes | E57: Gustavo | H57: Gustavo
A58: Verify user can able to active the inactive insurance payers by using "Active for some" | B58: 1.Launching the application 2.Enter the valid credential and click login button 3.Click the billing tab and access the Payers button. 4.Access the payers window opened 5.UnSelect the "hide inactive" checkbox, you will now able to see the inactive payer "opcode" in red clour. 6.Select one inactive payer and click on edit button. 6.Change the Active status by clicking the "Active for some" radio button. 7.Click the save button. 8.You will now able to see that payer "opcode" field is not in red colour and its in grey colour. 9.Select the "hide inactive" checkbox, you will now able to see the payer after selecting "hide inactive" checkbox. | C58: *User can active the inactive insurance payers *Inactive payer "opcode" field should be in grey colour | D58: Yes | E58: Gustavo | H58: Gustavo
A59: Verify the New Checkbox in Insurance Carrier Lookup Window | B59: 1.ogin to op 2. Open a patient's chart 3. Go to Account---> Insurance 4. Click the ... next to the insurance carrier 5.Check new hide inactive checkbox next to the inactive and not all labels at the bottom of the screen | C59: user should see New Checkbox in Insurance Carrier Lookup Window NOTE - hide inactive checkbox next to the inactive and not all labels at the bottom of the screen | H59: Gustavo
A60: Verify the New Checkbox Defaulted to Checked in the insurance carrier window | B60: l1.ogin to op 2. Open a patient's chart 3. Go to Account---> Insurance 4. Click the ... next to the insurance carrier 5. New hide inactive checkbox next to the inactive and not all labels at the bottom of the screen is defaulted to checked 6. And no inactive payers display in the grid | C60: user should see New Checkbox Defaulted to Checked in the insurance carrier window | H60: Gustavo
A61: verify the Inactive Payers in Insurance Carrier Lookup Window | B61: 1.Log into OP 2. Go to Billing --->Payers 3. Uncheck the hide inactive checkbox 4. Verify there are inactive payers in the list 5. Open a patient's chart 6. Go to Account---> Insurance 7. Click the ... next to the insurance carrier 8. Uncheck the hide inactive checkbox Then The inactive payers display in the grid | C61: User should see Inactive Payers in Insurance Carrier Lookup Window | H61: Gustavo
A62: verify the Search Ins by name or address | B62: l1.ogin to op 2. Open a patient's chart 3. Go to Account---> Insurance 4. Click the ... next to insurance carrier 5. Enter a name or address in the search field | C62: User should able to Search Ins by name or address NOTE:The grid filters and show results based on if the hide inactive checkbox is checked or not at the time of the search | H62: Gustavo
A63: Verify user can able to see " Include PWK Segment in Loop where an E&M code with a 25 modifier " checkbox under payer tab | B63: 1. Log into OP 2. Navigate to Billing 3. select payer 4. Create a new payer or Edit existing payer 5. Select " Payer Coding Rules" 6. Make sure below mentioned fields say [ when an E&M code..instead of when and E&M code....]. " Include PWK Segment in Loop where an E&M code with a 25 modifier " | C63: User should see " Include PWK Segment in Loop where an E&M code with a 25 modifier " check box under payer tab | H63: Gustavo
A64: Verify user can able to see the check box for "Include PWK segment in Loop2300 when an E&M code is billed with a 25 modifier" in Insurance payer Details window | B64: 1.Log into OP Application 2. Navigate to Billing 3. Select Payers under customize section 4. Make sure the insurance payers List window opened 5. select the existing payer and click edit or create one new payer. 6. Make sure the insurance payers Details window opened 7. Navigate to the Payer Coding Rules tab 8. Look under special claim coding rules: 9. make sure there is a check box for "Include PWK segment in Loop2300 when an E&M code is billed with a 25 modifier" | C64: User should see the check box for "Include PWK segment in Loop2300 when an E&M code is billed with a 25 modifier" in the Insurance payer Details window | H64: Gustavo
A65: Verify user can able to check "Include PWK segment in Loop2300 when an E&M code is billed with a 25 modifier" box and save | B65: 1.Log into OP Application 2. Navigate to Billing 3. Select Payers under customize section 4. Make sure the insurance payers List window opened 5. select the existing payer and click edit or create one new payer. 6. Make sure the insurance payers Details window opened 7. Navigate to the Payer Coding Rules tab 8. Look under special claim coding rules: 9. make sure there is a check box for "Include PWK segment in Loop2300 when an E&M code is billed with a 25 modifier" 10. Check the Include PWK segment in Loop2300 when an E&M code is billed with a 25 modifier check box 11. Click Save 12. Make sure the check box is saved | C65: Users should check "Include PWK segment in Loop2300 when an E&M code is billed with a 25 modifier" box and should save | H65: Gustavo
A66: verify "Include PWK segment in Loop2300 when an E&M code is billed with a 25 modifier" checkbox remains checked even when the user closes and opens the insurance payer details window for a payer. | B66: 1.Log into OP Application 2. Navigate to Billing 3. Select Payers under customize section 4. Make sure the insurance payers List window opened 5. select the existing payer and click edit or create one new payer. 6. Make sure the insurance payers Details window opened 7. Navigate to the Payer Coding Rules tab 8. Look under special claim coding rules: 9. make sure there is a check box for "Include PWK segment in Loop2300 when an E&M code is billed with a 25 modifier" 10. Check the Include PWK segment in Loop2300 when an E&M code is billed with a 25 modifier check box 7. Click Save 8.Close the insurance payer details window for a payer. 9. Again open the insurance payer details window for a payer(By clicking the Edit button) 10. Make sure the "Include PWK segment in Loop2300 when an E&M code is billed with a 25 modifier" checkbox is checked | C66: "Include PWK segment in Loop2300 when an E&M code is billed with a 25 modifier" checkbox remains checked even when the user closes and opens the insurance payer details window for a payer. | H66: Gustavo
A67: verify "Include PWK segment in Loop2300 when an E&M code is billed with a 25 modifier" checkbox remains checked even when the user closes and re-opens the insurance payer details window and Insurance payer List window . | B67: 1.Log into OP Application 2. Navigate to Billing 3. Select Payers under customize section 4. Make sure the insurance payers List window opened 5. select the existing payer and click edit or create one new payer. 6. Make sure the insurance payers Details window opened 7. Navigate to the Payer Coding Rules tab 8. Look under special claim coding rules: 9. make sure there is a check box for "Include PWK segment in Loop2300 when an E&M code is billed with a 25 modifier" 10. Check the Include PWK segment in Loop2300 when an E&M code is billed with a 25 modifier check box 7. Click Save 8. Close the insurance payer details window for a payer and Insurance payer List window. 9. Again open the Insurance payer List window and insurance payer details window for a payer(By clicking the Edit button) 10. Make sure the "Include PWK segment in Loop2300 when an E&M code is billed with a 25 modifier" checkbox is checked | C67: Include PWK segment in Loop2300 when an E&M code is billed with a 25 modifier" checkbox remains checked even when the user closes and re-opens the insurance payer details window and Insurance payer List window. | H67: Gustavo
A68: verify "Include PWK segment in Loop2300 when an E&M code is billed with a 25 modifier" checkbox remains checked even when the user closes and re-opens the insurance payer details window and Insurance payer List window and full Log out of OP application | B68: 1.Log into OP Application 2. Navigate to Billing 3. Select Payers under customize section 4. Make sure the insurance payers List window opened 5. select the existing payer and click edit or create one new payer. 6. Make sure the insurance payers Details window opened 7. Navigate to the Payer Coding Rules tab 8. Look under special claim coding rules: 9. make sure there is a check box for "Include PWK segment in Loop2300 when an E&M code is billed with a 25 modifier" 10. Check the Include PWK segment in Loop2300 when an E&M code is billed with a 25 modifier check box 7. Click Save 8. Close the insurance payer details window for a payer and Insurance payer List window and full Log out of OP application 9. Again login op application open the Insurance payer List window and insurance payer details window for a payer(By clicking the Edit button) 10. Make sure the "Include PWK segment in Loop2300 when an E&M code is billed with a 25 modifier" checkbox is checked | C68: "Include PWK segment in Loop2300 when an E&M code is billed with a 25 modifier" checkbox remains checked even when the user closes and re-opens the insurance payer details window and Insurance payer List window and full Log out of OP application | H68: Gustavo
A69: Verify user can able to UN-check "Include PWK segment in Loop2300 when an E&M code is billed with a 25 modifier" box and save | B69: 1.Log into OP Application 2. Navigate to Billing 3. Select Payers under customize section 4. Make sure the insurance payers List window opened 5. select the existing payer and click edit or create one new payer. 6. Make sure the insurance payers Details window opened 7. Navigate to the Payer Coding Rules tab 8. Look under special claim coding rules: 9. make sure there is a check box for "Include PWK segment in Loop2300 when an E&M code is billed with a 25 modifier" 10. UN-Check the Include PWK segment in Loop2300 when an E&M code is billed with a 25 modifier check box 7. Click Save 8. Make sure check box is saved | C69: Users should UN-check "Include PWK segment in Loop2300 when an E&M code is billed with a 25 modifier" box and should save | H69: Gustavo
A70: verify "Include PWK segment in Loop2300 when an E&M code is billed with a 25 modifier" checkbox remains UN-checked even when the user closes and opens the insurance payer details window for a payer. | B70: 1.Log into OP Application 2. Navigate to Billing 3. Select Payers under customize section 4. Make sure the insurance payers List window opened 5. select the existing payer and click edit or create one new payer. 6. Make sure the insurance payers Details window opened 7. Navigate to the Payer Coding Rules tab 8. Look under special claim coding rules: 9. make sure there is a check box for "Include PWK segment in Loop2300 when an E&M code is billed with a 25 modifier" 10. UN-Check the Include PWK segment in Loop2300 when an E&M code is billed with a 25 modifier check box 7. Click Save 8. Close the insurance payer details window for a payer. 9. Again open the insurance payer details window for a payer(By clicking the Edit button) 10. Make sure the "Include PWK segment in Loop2300 when an E&M code is billed with a 25 modifier" checkbox is UN-checked | C70: "Include PWK segment in Loop2300 when an E&M code is billed with a 25 modifier" checkbox remains UN-checked even when the user closes and opens the insurance payer details window for a payer. | H70: Gustavo
... A83: Verify when user Modifier NOT being added to telehealth services when POS is 10 and setting IS NOT populated in payer setup | B83: 1. log in to OP Application 2. Navigate to Billing > Payers 3. Create a new payer WITHOUT " Modifier for telehealth service: 95 under payer coding Rules or select the existing payer 4. Go to the patient chat 5. Select a patient with primary insurance WITHOUT Modifier for telehealth services setting is populated in the Payer coding rules of the payer setup Create a superbill where POS is 10 either manually or through clinical workflow Clinical Workflow 1. Open the patient Chart 2. Navigate to Encounters 3. Select New Encounter 4. Enter a CC and HPI 5. Select Visit Info 6. Select - [ office ] from the Telehealth provider location 7. Select - [ Home ] from the Telehealth provider location 8. Select Assess/Plan 9. Enter a Diagnosis Code (eg - z23) and Select the green check 10. Navigate to Coding, add CPT (eg - 99213 ) 11. Save and close Encounter Note 12. Go to the charges window and make sure there is a charge 13. Select the Superbill charges you just created in the Charges window 14. Click Post 15. make sure In the add/Edit charges window you should see that there is NO 95 modifier (mod 1 ) associated with the charges 16. Click Save 18.make sure charges are posted WITHOUT mod 95 Manual workflow 1. log in to OP Application 2. Navigate to Billing > Payers 3. Create a new payer WITHOUT " Modifier for telehealth service: 95 under payer coding Rules or select the existing payer 4. Go to the patient chat 5. Select a patient with primary insurance where the Modifier for telehealth services setting is populated in the Payer coding rules of the payer setup 6. Navigate to charges > click new super bill 7. Enter the mandatory fields ( participants, ICD-10 Description, CPT (Select POS - 10 ) 8. Click Exit 9. Click Post 10. make sure In the add/Edit charges window you should see that there is NO 95 modifier (mod 1 ) associated with the charges 11. Click Save 12. make sure charges are posted WITHOUT mod 95 | C83: Modifier NOT being added to telehealth services when POS is 10 and setting IS NOT populated in payer setup | H83: Gustavo
A84: Verify user able to add insurance payers | B84: 1.Launching the application 2.Enter the valid credential and click login button 3.Click the billing tab and access the Payers button. 4.Access the payers window opened 5.Add the new payer name by clicking New button. 6.Access the Insurance payer detail window opened. 7.Enter the details in below fields in basic information tab: *short code, *short name, *Full name, *Address, *city/state/zip 8.Navigate to claims/routing tab. 9.Fill the details for national payer id,claim payer id and real time id fields in claims/routing tab. 10.Click save button. | C84: Insurance payers should be added. | D84: Yes | E84: Gustavo | H84: Gustavo
A85: verify user can able to add insurance with own 6 digit short code | B85: 1.Launching the application 2.Enter the valid credential and click login button 3.Click the billing tab and access the Payers button. 4.Access the payers window opened 5.Add the new payer name by clicking New button. 6.Access the Insurance payer detail window opened. 7.Type the own 6 digit code and fill the required filed and click on save button. 8.Make sure sthe created insurance is searchable using the short code | C85: User can add a insurance with 6 digit short code | D85: Yes | E85: Gustavo | H85: Gustavo
A86: Verify the short name allow only 15 charater while creating the new insurance | B86: 1.Launching the application 2.Enter the valid credential and click login button 3.Click the billing tab and access the Payers button. 4.Access the payers window opened 5.Add the new payer name by clicking New button. 6.Access the Insurance payer detail window opened.7.type more than 15 charated in short name filed and 16th character should not be allowed to enter | C86: 16th character should not be allowed to enter by short name filed in Insurance payer details window | D86: Yes | E86: Gustavo | H86: Gustavo
A87: Check the staff can able to add/Update the insurance with Claims Routing | B87: 1.Launching the application 2.Enter the valid credential and click login button 3.Click the billing tab and access the Payers button. 4.Access the payers window opened 5.Add the new payer name by clicking New button. 6.Access the Insurance payer detail window opened. 7.Fill the basic informations and navigate to Claims/Routing tab and fill the details and save the insurance | C87: Staff should be able to add/update the insurnace with claims routing tab | D87: Yes | E87: Gustavo | H87: Gustavo
A88: Check the staff can able to add/Update the insurance with Payer Coding Rules and Contracts | B88: "1.Launching the application 2.Enter the valid credential and click login button 3.Click the billing tab and access the Payers button. 4.Access the payers window opened 5.Add the new payer name by clicking New button. 6.Access the Insurance payer detail window opened. 7.Fill the basic informations and navigate to Payer coding rule and fill the details 8.Click on Contracts tab and fill the required fileds and click on save | C88: Staff should be able to add/update the insurnace with payer coding rules and contract tab | D88: Yes | E88: Gustavo | H88: Gustavo
A89: Verify user can able to Edit the insurance using edit button | B89: 1. Launching the application 2. enter the valid credential and click login button 3. Click the billing tab and access the Payer button 4. access the insurance payer window. 5.Click the edit button. The Insurance Payer Details window opens to the Basic Information tab 6. modify the details for insurance 7. click save button | C89: Insurance payer should be updated | D89: Yes | E89: Gustavo | H89: Gustavo
A90: Check the staff can able to add a provider for newly added insurnace | B90: 1. Launching the application 2. enter the valid credential and click login button 3. Click the billing tab and access the Payer button 4. access the insurance payer window. 5.Add a new insurance 6.Expand the listed insurnace from the grid view from insurance payer list window 7.Click on + button and select the listed provider and select the active check box 8.Click on save button | C90: Staff should be add provider for newly added insurnace | D90: Yes | E90: Gustavo | H90: Gustavo
A91: Check the staff can able to add the provider for existing insurance | B91: 1. Launching the application 2. enter the valid credential and click login button 3. Click the billing tab and access the Payer button 4. access the insurance payer window. 5.Expand the listed insurnace from the grid view from insurance payer list window 6.Click on + button and select the listed provider and select the active check box 7.Click on save button | C91: Staff should be add provider for existing added insurnace | D91: Yes | E91: Gustavo | H91: Gustavo
A92: Check the Payer short name and the full name is displayed in Insurance Carrier Provider information window | B92: 1. Launching the application 2. enter the valid credential and click login button 3. Click the billing tab and access the Payer button 4. access the insurance payer window. 5.Expand the listed insurnace from the grid view from insurance payer list window 6.Click on + button and select the listed provider 7.MAke sure the short and full name of the provider is displayed | C92: Payer short and full name should displayed in Insurance Carrier Provider information window | D92: Yes | E92: Gustavo | H92: Gustavo
A93: Verify user can able to Associate an Insurance Contract with payer | B93: 1. Launching the application 2. enter the valid credential and click login button 3. Click the billing tab and access the Payer button 4. access the insurance payer window. 5.Click the edit button and navigate to contract tab 6. Click the New button from the Contract Chooser window, select the contract to associate with this payer and click Select. 7. If necessary, change the Effective date, Expiration Date, Location, or Provider using the drop-down. 8. click save button | C93: Payer should be Associate an with Insurance Contract | D93: Yes | E93: Gustavo | H93: Gustavo
A94: Verify user can able to delete the insurance using delete button | B94: 1. Launching the application 2. enter the valid credential and click login button 3. Click the billing tab and access the Payer button 4. access the insurance payer window. 5. select the insurance payer in the insurance window 6. click delete button | C94: Insurance payer should be deleted | D94: Yes | E94: Gustavo | H94: Gustavo
A95: Verify "Insurance Payer Details" window is closed when user click the "cancel" button | B95: 1. log in to OP 2. Navigate to the Billing tab 3. Navigate to the "Payer" tab 4. make sure the "Insurance Payer list window is opened 5. Click the New button 6. make sure "Insurance Payer Details" is opened 7. Click the "cancel" button 8. Make sure "Insurance Payer Details" is closed | C95: The "Insurance Payer Details" window should close when user click's when user click the "cancel" button | H95: Gustavo
A96: Verify user can able to print the insurance list using print button | B96: 1. Launching the application 2. enter the valid credential and click login button 3. Click the billing tab and access the Payer button 4. access the insurance payer window. 5.Click the print button to print list of insurance | C96: Insurance payer list should be printed | D96: Yes | E96: Gustavo | H96: Gustavo
A97: Verify user can able to copies payer/provider credentialing values from one selected payer to another, Information can be inserted or replaced using cred button | B97: 1. Launching the application 2. enter the valid credential and click login button 3. Click the billing tab and access the Payer button 4. access the insurance payer window. 5. select the two insurance payer in the insurance window 6. click cred button to copy one payer details to another payer details | C97: Insurance payer should be copies one selacted to another payer | D97: Yes | E97: Gustavo | H97: Gustavo
A98: Verify user can able to export the insurance payer information in Xml format using export button | B98: 1. Launching the application 2. enter the valid credential and click login button 3. Click the billing tab and access the Payer button 4. access the insurance payer window. 5. select the insurance payer in the insurance window 6. click export button to download the payer details | C98: Payer details should be exported | D98: Yes | E98: Gustavo | H98: Gustavo
A99: Verify user can able to import the insurance payer information in Xml format using import button | B99: 1. Launching the application 2. enter the valid credential and click login button 3. Click the billing tab and access the Payer button 4. access the insurance payer window. 5. select the insurance payer in the insurance window 6. click import button to add a new the payer details | C99: Payer details should be imported | D99: Yes | E99: Gustavo | H99: Gustavo
A100: Verify user can able to view the corrosponding provider for the payer using expand grid check box | B100: 1. Launching the application 2. enter the valid credential and click login button 3. Click the billing tab and access the Payer button 4. access the insurance payer window. 5. select the expand grid check box to view the corrosponding provider for the payer 6. verify provider details are displayed | C100: Payer details should be expanded | D100: Yes | E100: Gustavo | H100: Gustavo
A101: Verify user can able to view the inactive payer by unchecking the hide inactive checkbox | B101: 1. Launching the application 2. enter the valid credential and click login button 3. Click the billing tab and access the Payer button 4. access the insurance payer window. 5. unchecking the hide inactive check box to view the inactive payer 6. verify inactive payer details are displayed | C101: Inactive payer details should be displayed | D101: Yes | E101: Gustavo | H101: Gustavo
A102: Verify user can able to associated new providers for this payer. | B102: 1. Launching the application 2. enter the valid credential and click login button 3. Click the billing tab and access the Payer button 4. access the insurance payer window. 5. Click the small Insert Record button to the left of the Insurance Payer Name 6. click added button to associated the provider for this payer. 7. click on save button 8. verify the listing will expand, displaying associated providers for this payer. | C102: User should able to see the associated providers for this payer by expanding the list | D102: Yes | E102: Gustavo | H102: Gustavo
A103: Verify user can able to associated edit providers for the listed insurance | B103: 1. Launching the application 2. enter the valid credential and click login button 3. Click the billing tab and access the Payer button 4. access the insurance payer window. 5. Click the small Insert Record button to the left of the Insurance Payer Name 6. click edit button to associated the provider for this payer and click save button 7. verify the listing will expand, displaying associated providers for this payer. | C103: Staff should able to edit the provider information which is associated with insurance | D103: Yes | E103: Uday | H103: Gustavo
A104: Verify the updated value is getting reflected while click on refresh button from the provider section | B104: 1. Launching the application 2. enter the valid credential and click login button 3. Click the billing tab and access the Payer button 4. access the insurance payer window. 5. Click the small Insert Record button to the left of the Insurance Payer Name 6. click edit button to associated the provider for this payer and click save button 7. Click on refresh button and make sure the updated values are getting overwright the previous value | C104: Updated provider details should be reflected while click on refresh button | D104: Yes | E104: Uday | H104: Gustavo
A105: Verify the staff can able to delete the listed provider | B105: 1. Launching the application 2. enter the valid credential and click login button 3. Click the billing tab and access the Payer button 4. access the insurance payer window. 5. Expand the insurance from insurance payer list 6.click on delete button | C105: Staff should be delete the listed provider from the insurance list | D105: Yes | E105: Uday | H105: Gustavo
A106: Verify the staff can able to remove the provider for insurance | B106: 1. Launching the application 2. enter the valid credential and click login button 3. Click the billing tab and access the Payer button 4. access the insurance payer window. 5. Expand the insurance from insurance payer list 6.Un check the Active checkbox | C106: Provider should be removed from the insurance section while uncheck the active check box | D106: Yes | E106: Uday | H106: Gustavo
A107: Verify Providers are not Add under the insurance payers list window when the user clicks the "cancel " or "X" button under the insurance Carrier provider information window | B107: 1. log in to op application. 2. Click the Billing tab in the top menu. 3. Click the Payers in customize section. 4. Insurance payers list window should open. 5. Choose any insurance payer and expand the grid. 6. Click Add("+") icon, Insurance provider carrier information window should open. 7. Choose a provider in the dropdown and check the Active checkbox. 8. Close the window without clicking the save button. 9. Make sure the selected provider is not added under the insurance payers list window | C107: Providers should not Add under the insurance payers list window when the user clicks the "cancel " or "X" button under the insurance Carrier provider information window | H107: Gustavo
A108: Verify when user Closing out with the X provider is not saved or added to the list under the insurance carrier | B108: 1. log in to the op application. 2. Navigate to Billing > Payers 3. Expand an Insurance Carrier 4. Click Add("+") icon and the Insurance provider carrier information window opens 5. Choose a provider in the dropdown and check the Active checkbox. 6. Close the window with the X in the top right corner 7. Verify the provider is not saved or added to the list under the insurance carrier | C108: Closing out with the X provider should not saved or added to the list under the insurance carrier | D108: Yes | E108: Uday | H108: Gustavo
A109: Verify when user Closing out with clicking Cancel provider is not saved or added to the list under the insurance carrier | B109: 1. log in to the op application. 2. Navigate to Billing > Payers 3. Expand an Insurance Carrier 4. Click Add("+") icon and the Insurance provider carrier information window opens 5. Choose a provider in the dropdown and check the Active checkbox. 6. Close the window with the Cancel button 7. Verify the provider is not saved or added to the list under the insurance carrier | C109: Closing out with clicking Cancel provider should not saved or added to the list under the insurance carrier | D109: Yes | E109: Uday | H109: Gustavo
A110: Verify when user Closing out with clicking Save provider is saved or added to the list under the insurance carrier | B110: 1. log in to the op application. 2. Navigate to Billing > Payers 3. Expand an Insurance Carrier 4. Click Add("+") icon and the Insurance provider carrier information window opens 5. Choose a provider in the dropdown and check the Active checkbox. 6. Close the window by clicking save button. 7. Verify the selected provider is added | C110: Closing out by clicking Save provider should saved or added to the list under the insurance carrier | D110: Yes | E110: Uday | H110: Gustavo
A111: Verify User can able to Add Providers Name and check displays under the expanded insurance carrier window Without click on Refreshes button - with Active check box | B111: 1.Log on to OP with valid credentials 2. Navigate to the billing tab > Payer 3. Insurance payers List Window opens 4. Select any payer 5.click on the + icon On Left side 6. Expand Grid Opens 7. Click on the + icon 8. Select a provider from the Provider dropdown 9. Check Active 10. Click Save 11. Ensure Providers Name Appears | C111: User should Add Providers Name and should displays under the expanded insurance carrier window Without click on Refreshes button - with Active check box | D111: Yes | E111: Uday | H111: Gustavo
A112: Verify user are able to access the contracts window | B112: 1. Launching the application 2. enter the valid credential and click login button 3. Click the billing tab and access the contracts button 4. access the contracts payer window. | C112: User should be access the contract window | D112: Yes | E112: Uday | H112: Gustavo
A113: Verify user are able to add a new contract using new(+) button | B113: 1.Launching the application 2.Enter the valid credential and click login button 3.Click the billing tab and access the contracts button. 4.Access the contracts window opened 5.Add contracts by clicking the plus icon. 6.New Insurance contract window is getting poped up. 7.Select either Non-Vaccine, Vaccine Only, All CPTs, or None in New Insurance contract window 8.Click the Save button 9.Add New contract name and Save the details by clicking select icon. 10.Check whether the added contracts are reflected. | C113: New Contracts should be added | D113: Yes | E113: Uday | H113: Gustavo
...

Sheet Nurse
B1: STEPS | D1: Owner - FB(High level) | E1: Status | F1: Comment | G1: Owner - MySQL(Full regression) | H1: Status | I1: Comment
A3: Location
A4: Verify User Can Select and Change Location | B4: 1. Login as Nurse. 2. ✅ Verify that a location selection pop-up appears upon login. Note: The location selection pop-up appears only on the first login of the application. 3. ✅ Ensure the user can change the location based on assigned locations. 4. Navigate to the Clinical tab in the main panel. 5. Click on the Schedule icon to open the My View page in the calendar window. 6. Select the location from the calendar dropdown. 7. ✅ Verify that the user can successfully change the location in the calendar view based on assigned locations. | G4: Thara
A5: Clinical Tab Functionalities
A6: Verify User Can Able To Access Clinical Tab & its Functionalities | B6: 1.Login as Nurse. 2.Ensure the CLINICAL tab is displayed in the header section after login. 3.Click on the CLINICAL tab and ✅verify the following icons are displayed and accessible: 3.1. Patient Chart → Opens the Patient Chart. 3.2. Tasks → Opens the Tasks window. 3.3. Send Message → Opens the Send Message window. 3.4. Address Book → Opens the Address Book window. 3.5. Document Mgmt → Opens the Document Management window. 3.6. Medical Records → Opens the Medical Records window. 3.7. School/Camp Reports → Opens the Patient Medical Reports Manager. 3.8. Care Plans → Opens the Manage Care Plans: Global window. 3.9. Phrases → Opens the Phrase Construction window. 3.10. More - Diagnostic Tests → Opens the HL7 Diagnostic Test Utilities. 3.11. More - Graphical Milestones → Opens the Developmental Milestones Choice List. 3.12. More - Patient Education → Opens the AAP/Local Content Library. 3.13. More - Web/PDF Resources → Opens tabs for Web and PDF Resources. 3.14. More - Customize CDA → Opens the Customize CDA window. 3.15. Diagnosis Codes → Opens the Diagnosis Code Management window. 3.16. Procedure (CPT) Codes → Opens the CPT-4 window. 3.17. More - Allergy Codes → Opens the E-Prescriber Allergy Data mapping window. 3.18. More - Immunization Codes → Opens the Vaccine admin routes window. | C6: Yes | D6: Thara | G6: Thara
A7: Appointment
A8: Verify user able to schedule a new appointment (sick visit, well visit, PPD visit, PPD reading, placeholder, nurse visit) for a patient in the schedule window. | B8: 1.Login as Nurse. 2.Select the "Clinical" tab in the top-left corner of the window. 3.Click on the "Schedule" icon. 4.Select "My View" option and click the location dropdown (i.e.,Down arrow). 5.Choose the primary location. 6.Choose the time slot and double-click on the slot. 7.The "Add/Edit Appointment" window will be displayed. 8.Search for the patient in the search box and click the search icon. 9.✅Verify that the patient information is listed in the respective dropdowns. 10.Fill in the required fields, including: 10.1. Appointment Reason (Sick Visit, Well Visit, PPD Visit, Nurse Visit) 10.2. Appointment Type 11.Click the "Save" button. 12.✅Verify that the new appointment appears in the scheduled time slot. | C8: Yes | D8: Thara | G8: Thara
A9: Verify the User Can Open the Well Visit, from Tracking Window or Calendar Window | B9: 1. Log in as a Nurse. 2. Click the Schedule icon and navigate to the My View page. 3. Perform one of the following actions to open the Well Visit: 3.1. Select a scheduled patient appointment and right-click using the mouse. 3.2. Click on the Menu icon in the Tracking window and select Open Well Visit. 3.3. Right-click on the scheduled patient appointment in the Calendar and select Open Well Visit. 4. ✅ Ensure that the Interval HX tab opens successfully. | C9: Yes | D9: Thara | G9: Thara
A10: Verify the Confirmation Prompt and template in Well visit/Encounter note Confirmation Prompt Messages: In Encounter: The app is associated with template named. Would you like to apply this template In Well visit: Do you wish to use the default template for age? | B10: 1. Log in as a Nurse. 2. Click the Schedule icon and navigate to the My View page. 3. Right-click on the patient appointment in the Tracking window and select Open Well Visit/Open Encounter. 4. ✅ Check the confirm popup window is displayed. 4.1. Click the "NO" button 4.1.1. In Well Visit → ✅ Check that a new template is displayed (the associated template with the appointment should not appear in the Interval History info; it should display a blank template). 4.1.2. In Encounter → ✅ Check that a new template is displayed (the associated template with the appointment should not appear in the CC info; it should display a blank template). 4.2. Click the "YES" button 4.2.1. In Well Visit → ✅ Check that the associated template with the appointment is displayed in the Interval History info of the Well Visit note. 4.2.2. In Encounter → ✅ Check that the associated template with the appointment is not displayed in the CC info of the Encounter note. | C10: Yes | D10: Thara | G10: Thara
A11: Verify the appointments (without Appt reason and Appt type) should not be listed in the tracking window. | B11: 1.Login as Nurse 2.Navigate to schedule window using Clinical icon 3.Create an appointment without Appt reason nor Appt type 4.✅Verify user able to create appointment withou Appt reson nor Appt type. 5.Navigate to tracking window by clicking on Tracking radio button 6.✅Created appointment should not be displayed | C11: Yes | D11: Thara | G11: Thara
A12: Schedule - Tracking
A13: Verify User Can Able To Access Tracking Window and Related Functionalities . | B13: 1. Login as Nurse. 2. Click on the Schedule icon. 3. ✅ Verify that the "My View" screen is accessible. 4. Click on the Tracking Window and verify the following actions can be performed: 4.1. ✅ Ensure that the Tracking Window displays the following columns: \[Staff Name, Time, Patient, Reason, TOV, Arrival, Room, Visit Status, Min, Tasks, Billing Status, Ins. Valid, Verification #, Check Out, Pat Pay, Confirm Status, Curbside Status]. 4.2. ✅ Check if the logged-in staff name and the list of assigned patients appear in the Tracking View. 4.3. ✅ Verify that the user can drag the following columns in and out of the sort header: \[Staff, Patient, Reason, TOV, Arrival, Room, Visit Status, Billing Status, Curbside Status, Portal Account]. 4.4. ✅ Date Selection → The user can manually type or select a date from the calendar to view patient appointments for a specific date. 4.5. ✅ Show Tasks Filter → Selecting All, Mine, or Selected Department should update the Tasks column accordingly. 4.6. ✅ Expand/Collapse Grid → Checking/unchecking Expand Grid should show/hide entries. 4.7. ✅ Auto Refresh → Enabling Auto Refresh should keep the window updated in real time. 4.8. ✅ Exclude Checked Out → Checking this option should hide patients who have checked out. 4.9. ✅ Exclude Not Checked In → Checking this option should hide patients who have not checked in. 4.10. ✅ Show Billing Panel → Checking this should display billing transactions or superbill entries. 4.11. ✅ Print Tracking Schedule → Clicking Print should open a print preview with the tracking window details. 4.12. ✅ Validate Insurance → Clicking Validate should open the Insurance Validation window. | C13: Yes | D13: Thara | G13: Thara
A14: Verify User Can Able To Access Patient Details (sick visit, well visit, PPD visit, nurse visit) In Appoinment Table Of The Tracking Window | B14: 1.Login as Nurse 2.Click on the Schedule icon. 3.Verify that the "My View" screen is accessible 4.Click on Tracking Window and Verify the following actions are able to perform in the patient details grid. 4.1. ✅Time Column → User cannot change the visit time. 4.2. ✅Arrival Time → User can adjust the arrival time using arrows. 4.3. ✅Check-in Clock → Clicking the Check-in Clock should log a check-in time. 4.4. ✅Checkout Clock → Clicking the Checkout Clock should log the current time as the checkout time. 4.5. ✅Checkout Time Adjustment → User can manually adjust checkout time using the up/down arrows. 4.6. ✅Room Dropdown → User can change the room assignment. 4.7. ✅Visit Status Dropdown → User can change visit status. 4.8. ✅Billing Status Dropdown → User can select different billing statuses 4.9.✅Sigma (Patient Tracking Summary) → Clicking Sigma should open the Patient Tracking Summary window. 4.10. ✅Insurance Validation for Single Patient → Clicking the green check icon should validate insurance for a single patient. 4.11.✅ Confirm Status Dropdown → User can update confirmation status. 4.12. ✅Portal Account Status → Should show Active/Inactive based on the patient. 4.13.✅ Right-click a patient and access the Menu → Verify the following options are available: [Open Encounter, Open Well Visit, Add/Edit Appointment, Print, Clear Room Assignment, Clear Visit Status, Clear Billing Status, Clear Checkout Time, Clear All Fields, Print Reports.] | C14: Yes | D14: Thara | G14: Thara
A15: Verify user can Update Portal Accounts | B15: 1.Login as Nurse 2.Click Schedule icon and navigate to My view page 3.Click the Tracking radio button 4.Click on "Update Portal Accounts " Button 5.Make sure the portal Account column will update based on new Portal Account statuses picked up by the update process | G15: N/A
A16: Note: An appointment should be created and validated. Verify each respective tab (such as Vitals/Growth, Allergies, etc.) for Encounter, Well Visit, and Nurse Visit notes. A separate appointment should be created for each note type.
A17: Wellvisit - Interval HX
A18: Verify the Interval Hx tab is displayed on the left panel, is clickable, and opens the Interval History and ROS screen when clicked. | B18: 1. Login as Nurse. 2. Click the schedule icon under the clinical tab and click the tracking radio button. 3. Select a scheduled appointment for a patient and right-click using the mouse. 4. Click "Open well visit" option. 5. Click on the Interval Hx tab and verify:The Interval Hx window opens up. ✅Interval HX tab should be displayed on the left panel and should be clickable 5.1. The Interval History and ROS screen appears. ✅Interval History and ROS screen should open when user clicks on Interval Hx tab | C18: Yes | D18: Thara | G18: Thara
A19: Verify the following elements are visible and functional on the Interval Hx tab: 1. 'Show All Groups' checkbox can be checked. 2. Custom Questions drop-down is clickable along with the free text box. 3. 'Add' button for Custom Questions is clickable. 4. 'Complete List' button is clickable. 5. 'Prior Notes' button is clickable. | B19: 1. Login as Nurse 2. Access Schedule > Tracking > Right-click patient appointment > Open well visit > Interval Hx tab. 3. Perform actions and verifications: 4. Show All Groups: ✅ Check/uncheck ROS box to display all groups or only those with documented ROS. 4.1. Custom Questions: ✅ Dropdown visible with options (Well Visit: Infant to Allergic/Immunologic). 4.2. Add custom category/question > ✅ Added successfully. 4.3. Error handling: Click Add without category/question > ✅ Error pop-up "Please enter a category and question to add". 4.4. Complete List button: ✅ Access Complete List of Well Visit Templates. 4.5. Prior Notes: ✅ Access list of all prior notes. | C19: Yes | D19: Thara | G19: Thara
A20: After clicking 'Prior Notes', verify that the user can: 1. Check the box for "Exclude negative ROS/ normal exam findings". 2. Apply Entire Note using the 'Apply Entire Note' button 2. Choose to Apply Entire Note using the 'Apply Entire Note' button, which displays a pop-up: "This operation will overwrite data in all fields. Continue? Yes. No." 3. Choose to apply the exam only using the 'Apply Exam Only' button. 4. Click the View Summary/Addenda button. | B20: 1. Login as Nurse 2. In Schedule > Tracking > Right-click patient appointment > Open well visit > Interval Hx tab. 3. Click Prior Notes > Perform actions and verifications: 4. Exclude negative ROS/normal exam findings: ✅ Check/uncheck box to include/exclude. 5. Apply Entire Note: 5.1. Click Apply Entire Note > ✅ Warning pop-up "Overwrite data in all fields?" 5.2. Click Yes > Data overwritten; Click No > Returned to Interval Hx. "Overwrite data in all fields?" 5.3. Apply Exam Only: Click Apply Exam Only > ✅ Warning pop-up "Overwrite [School Exam] and [Detailed Exam] sections?" 5.4. View Summary/Addenda: ✅Click View Summary/Addenda > User can view note summary/addenda. | C20: Yes | D20: Thara | G20: Thara
A21: Verify staff can: 1. Edit or add a value in the Interval History text box. 2. Mark past medication history using the following symbols: to report (1 mouse click) to deny (2 mouse clicks) Pert (3 mouse clicks) 3. Add comments for listed ROS from Interval Hx. | B21: 1. Login as Nurse 2. In Schedule > Tracking > Right-click patient appointment > Open well visit > Interval Hx tab. 3. Verify functionality: 4. Adding comments: ✅ User can edit/add text to Interval History Text Box. 5. Marking past medication history: 5.1. ✅ User can mark with symbols: (Pert)-Yellow + (confirm) Green, - (denies)-Red, (Skip)-white. 6. Adding ROS comments: 6.1. ✅ Staff can edit, save, and verify comments for listed ROS. | C21: Yes | D21: Thara | G21: Thara
A22: Add a custom question in history tab. | B22: 1.Login as Nurse. 2. Access the Clinical/Billing/Practice Management tab and open the patient chart. 3. Search and select a patient using Patient Finder. 4. Click the History hyperlink under the Clinical section to open the History page. 5. Select a custom category (e.g., Past Medical, Social, Newborn), enter data, and save the custom question. 6. Verify the custom question is saved successfully. - ✅ Custom question should be added in history tab. | C22: Yes | D22: Thara | G22: Thara
A23: Verify that a newly added custom question remains visible and does not disappear when the user navigates to other tabs. | B23: 1.Login as Nurse. 2.In Clinical/Billing/Practice Management > Patient Chart > Search/select patient > History. 3. For each tab (Past Medical, Social, Newborn): 4. Add custom question > Save > 5. Navigate to other tabs/sections (Allergies, Immunization) > Return > 6. For each of the following tabs: Past Medical - ✅ Newly added custom question should not disappear, when user navigates to other tabs. 6.1. Social - ✅ Newly added custom question should not disappear, when user navigates to other tabs. 6.2. Newborn: ✅ Newly added custom question should not disappear, when user navigates to other tabs. | C23: Yes | D23: Thara | G23: Thara
A24: Verify user can able to see the Click Note Type in summary page on well visit note. | B24: 1. Login as Nurse.. 2. Click on the Patient Chart under the Clinical tab. 3. Select a patient using the Patient Finder. 4.Go to well visit and Click New note button. 5. Fill in the required fields (IntervalHX). 6. Navigate to the Summary page. 7. Verify that the user can view the Click Note Type on the Summary page - ✅User should see the Click Note Type in summary page on well visit note. | C24: Yes | D24: Thara | G24: Thara
A25: Verify the Clinical note type will order the below options, when user click the Clinical Note Type button in summary page on wellvisit note. | B25: 1. Login as Nurse. 2. Select patient using Patient Finder > Create new note (Well Visit). 3. Fill required fields IntervalHX> Navigate to Summary page. 4.✅ Verify that the following Clinical Note Type options are displayed when the user clicks the Clinical Note Type button on the Summary page of the Well Visit note: Progress Note Consultation Note History & Physical Procedure Note Imaging Narrative Discharge Summary Note | G25: Thara
A26: Verify when user select the below options in Clinical Note Type on summary page, the LOINC code reflects in Database viewer tab for the respective options for a patient on well visit note. | B26: 1. Login as Nurse 2. Select patient > Create new note (Well Visit) 3. Fill required fields (IntervalHX) > Go to Summary page 4. Select Clinical Note Type options: - Progress Note (11506-3), Consultation Note (11488-4), History & Physical (34117-2), Procedure Note (28570-0), Imaging Narrative (18748-4), Discharge Summary Note (18842-5) 5. Navigate to Tools > Click Database viewer 6. Select SQL and run using the query (i.e DB Viewer - SQL - Select*from physical where patno = 9313.) ✅ Verify that the LOINC code reflects in the Database Viewer tab for the respective options for a patient on the Well Visit note | G26: Thara
A27: Encounter - CC/HPI/ROS Tab
A28: Verify Sick Visit Encounter Note Creation with Template Confirmation and CC Auto-Population | B28: 1. Login as Nurse 2. Click the Schedule icon under the Clinical tab. 3. Select the Tracking radio button to switch to the tracking view. 4. Select a scheduled sick visit appointment for a patient and right-click using the mouse. 5. Select "Open Encounter" from the right-click menu. 6. ✅ Verify that a template confirmation popup is displayed, prompting the user to select or edit a template before proceeding. 7. Select a template that includes a predefined Chief Complaint (CC). 8. ✅ Verify that the staff is able to access the CC/HPI/ROS tab. 9. ✅ Verify that the CC field is auto-populated based on the selected template. | C28: Yes | D28: Thara | G28: Thara
A29: Verify Adding Sub CC via Template Search and Confirmation Popup | B29: 1. Login as a Nurse. 2. Click the Schedule icon under the Clinical tab. 3. Select the Tracking radio button. 4. Select the scheduled patient appointment, right-click using the mouse, and click Open Encounter Note. 5. Navigate to the CC/HPI/ROS page. 6. In the "All Template"search field, search for and select a Sub CC template. 7. ✅ Verify that a confirmation popup appears for adding the new Sub CC. 8. When the confirmation popup appears, click Yes. 9. ✅ Verify that the Sub CC is added and the associated symptoms and comments are correctly displayed in the CC/HPI/ROS screen. | C29: Yes | D29: Thara | G29: Thara
A30: Verify User Can Select Templates Based on Author or All in Encounter Note | B30: 1.Login as a Nurse. 2.Click the Schedule icon under the Clinical tab. 3.Select the Tracking radio button. 4.Select a scheduled appointment for a patient and right-click using the mouse and open the Encounter Note. 5.Navigate to the CC/HPI/ROS tab. 6.In the top-left section, click the template source drop-down. 7.Select All Templates: 7.1.✅ Verify that the second drop-down to select a provider is not displayed. 7.2.✅ Confirm that templates are listed and can be selected without errors. 8.Select Author Specific: 8.1.✅ Verify that the provider drop-down is now visible to the right. 8.2.✅ Select a provider from the list and confirm that only templates assigned to that provider are displayed. 8.3.✅ Ensure template selection works without errors. | C30: Yes | D30: Thara | G30: Thara
A31: Verify that the user can apply any template in the Complete List by single-clicking on the Paperclip icon next to the desired template | B31: 1.Login as Nurse. 2.Click the Schedule icon under the Clinical tab. 3.Select the Tracking radio button. 4.Select a scheduled appointment for a patient and right-click using the mouse and open the Encounter Note. 5.Navigate to the CC/HPI/ROS tab. 6.In the top-left section, click the drop-down to access templates. 7.Click on the Complete List button. 8.✅ Verify that it navigates to the Complete List of Encounter Templates. 9.Locate a desired template in the list. 10.Click the "+" (plus) symbol next to the template to expand its view. 11.Click the Paperclip icon next to the desired template. 12.When the confirmation popup appears, click Yes. 13.✅ Verify that the Apply Template dialog box is displayed. | C31: Yes | D31: Thara | G31: Thara
A32: Verify that the survey is validated in the CC/HPI/ROS tab. | B32: 1. Login as Nurse. 2. Click the Schedule icon under the Clinical tab. 3. Select the Tracking radio button. 4. Select a scheduled appointment for a patient, right-click using the mouse, and open the Encounter Note. 5. Navigate to the CC/HPI/ROS tab. 6. Click on the Complete List button. 7. Click the Validate Survey button. 8. ✅ Verify that the Validate Surveys window launches, allowing survey validation, or an information box appears stating "All surveys are valid." | C32: Yes | D32: Thara | G32: Thara
A33: Verify the functionality of the Prior Notes section in the CC/HPI/ROS tab. | B33: 1.Login as Nurse. 2.Click the Schedule icon under the Clinical tab. 3.Select the Tracking radio button. 4.Select a scheduled appointment for a patient and right-click using the mouse and open the Encounter Note. 5.Navigate to the CC/HPI/ROS tab. 6.Click the Prior Notes button ✅ Verify: The Prior Notes window opens. 7.Select the Encounter item from the grid 8.Ensure the following actions are performed when clicking the following buttons in Prior Notes Window : 8.1.Click the Apply to Current Encounter button -> ✅ Verify: User is returned to the CC/HPI/ROS tab and selected content is auto-filled into the CC textbox. 8.2. Click View/Edit Note & Addenda button -> ✅ Verify: User is brought back to the CC/HPI/ROS screen with the selected encounter displayed (when unfinalized encounter is selected) | C33: Yes | D33: Thara | G33: Thara
A34: Precondition: The patient should have already sent a message, which should be displayed in the grid under the Prior Notes window. Verify that the 'View/Edit Note & Addenda' option is only enabled for Encounter items in the Prior Notes grid. | B34: 1.Login as Nurse. 2.Click the Schedule icon under the Clinical tab. 3.Select the Tracking radio button. 4.Choose a patient and open the Encounter Note. 5.Navigate to the CC/HPI/ROS tab. 6.Click the Prior Notes button. 7.In the Prior Notes window, observe the 'View/Edit Note & Addenda' button. 8.Select a non-encounter item (e.g., Message). 9.Click the 'View/Edit Note & Addenda' button. 10.✅ Verify the following warning message appears:"The view/edit function is available for encounters only." | C34: Yes | D34: Thara | G34: Thara
A35: Verify the Functionality of the + Add CC/HPI Button in the CC/HPI/ROS Tab | B35: 1.Login as Nurse. 2.Click the Schedule icon under the Clinical tab. 3.Select the Tracking radio button to display patient appointments. 4.Select the patient and open the Encounter Note. 5.Navigate to the CC/HPI/ROS page. 6.Click the + Add CC/HPI button located below the HPI text box. 7.✅ Verify that the blank CC/HPI/ROS window should display, or a warning message should appear stating that the current CC box cannot be blank. | C35: Yes | D35: Thara | G35: Thara
A36: Verify that the user can see and click the Delete button below the HPI text box. | B36: 1.Login as Nurse. 2.Click the Schedule icon under the Clinical tab. 3.Select the Tracking radio button to access the list of scheduled patient appointments. 4.Select the scheduled patient appointment and Right click-> select open the Encounter Note. 5.Navigate to the CC/HPI/ROS page. 6.Click the Delete button below the HPI text box. 7.✅ Verify that the blank CC/HPI/ROS window is displayed, or a warning message appears stating that the current CC box cannot be blank. 8.✅ Verify that a confirmation box is shown with the following message: "Delete the displayed CC/HPI? Ok. Cancel." | G36: Thara
A37: Verify Navigation of CCs Using < > Arrows in Encounter Note | B37: 1.Login as Nurse. 2.Click the Schedule icon under the Clinical tab. 3.Select the Tracking radio button to access the list of scheduled patient appointments. 4.Select the scheduled patient appointment and Right click-> select open the Encounter Note.. 5.Navigate to the CC/HPI/ROS page. 6.If there is only 1 CC/HPI/ROS, ensure that the < > arrows are greyed out and not clickable. 7.Click on the + Add CC/HPI button below the HPI text box. 8.Add a new CC/HPI entry. 9.✅ Verify that if there are more than 1 CC/HPI/ROS, the < > arrows will navigate the user back and forth between the applied CC/HPI/ROS windows. | G37: Thara
A38: Verify access to the HPI drop-down fields and the functionality of the HPI free-text field. | B38: 1.Login as Nurse. 2.Click the Schedule icon under the Clinical tab and click the Tracking radio button. 3.Select the patient and open the Encounter Note. 4.Navigate to the CC/HPI/ROS page. 5. ✅ Verify that the user can access and select values from the following drop-down fields: [Location, Timing/Onset, Duration/Pattern, Severity, Quality] 6.✅ Verify that the user can type into the HPI free-text field. 7.✅ Verify that anything typed in the HPI free-text field is auto-saved when the user navigates to another tab within the visit. | G38: Thara
A39: Verify access to the Show All Groups checkbox in the CC/HPI/ROS window. | B39: 1.Login as Nurse. 2.Click the Schedule icon under the Clinical tab and click the Tracking radio button. 3.Select the patient and open the Encounter Note. 4.Navigate to the CC/HPI/ROS page. 5.✅ Verify that the user can check the 'Show All Groups' check-box to the right of ROS -> all groups are displayed 6.✅ Verify that the user can un-check the 'Show All Groups' check-box to the right of ROS -> only groups with documented ROS are displayed. | G39: Thara
A40: Verify the user can see the following column headers in the Detailed ROS tab: Rpt/Deny, Question/Symptom, Comment, QUESTION_ID, VALUE_ID, Phrase Construction Icon. | B40: 1. Login as Nurse. 2. Click the Schedule icon under the Clinical tab and click the Tracking radio button. 3. Select the patient and open the Encounter Note. 4. Navigate to the CC/HPI/ROS page. 5. Click the Detailed ROS tab under the ROS header. 6. ✅ Verify that the user can click the top-left corner of the Detailed ROS box, as indicated by the hover message: 'Click here to show/hide/move column'. | G40: Thara
A41: Verify Freeform ROS Text Box Allows Input and Auto-Saves Upon Navigation | B41: 1.Login as Nurse. 2.Click the Schedule icon under the Clinical tab and select the Tracking radio button. 3.Select a patient and open the Encounter Note. 4.Navigate to the CC/HPI/ROS page. 5.Click the Freeform ROS tab under the ROS section. 6.Type text into the Freeform ROS text box. 7.✅ Ensure that user is able to type freely into the Freeform ROS text box. 8.Navigate away from the CC/HPI/ROS tab (e.g., to Vitals or Problem List tab). 9.Return to the CC/HPI/ROS tab. 10.✅ Verify that the text entered in the Freeform ROS box is still present. | G41: Thara
A42: Verify All The Following ROS Groups Are Visible and Expandable in the Detailed ROS Tab [Constitutional, Eyes, ENT, Respiratory, Cardiovascular, Gastrointestinal, Genitourinary (M/F), Musculoskeletal, Integumentary (Skin/Breast), Hematologic/Lymphatic/Immunologic, Endocrinology, Neurologic, Psychiatric, Allergic/Immunologic, Breastfeeding: Infant, Breastfeeding: Mother, Medical Home, Flu Immunization] | B42: 1.Login as Nurse. 2.Click the Schedule icon under the Clinical tab. 3.Select the Tracking radio button. 4.Choose a patient and open the Encounter Note. 5.Navigate to the CC/HPI/ROS page. 6.Click the Detailed ROS tab under the ROS section. 7.✅ Verify that the user can view, expand, and collapse each of the following groups:[Constitutional, Eyes, ENT, Respiratory, Cardiovascular, Gastrointestinal, Genitourinary (M/F), Musculoskeletal, Integumentary (Skin/Breast), Hematologic/Lymphatic/Immunologic, Endocrinology, Neurologic, Psychiatric, Allergic/Immunologic, Breastfeeding: Infant, Breastfeeding: Mother, Medical Home, Flu Immunization] | G42: Thara
A43: Verify Custom Questions Functionality in CC/HPI/ROS Tab | B43: 1.Login as Nurse. 2.Click the Schedule icon under the Clinical tab. 3.Select the Tracking radio button. 4.Choose a patient and open the Encounter Note. 5.Navigate to the CC/HPI/ROS page. 6.✅ Verify the Custom Questions field is visible at the bottom of the CC/HPI/ROS window, including: a drop-down labeled "Group" and a free-text input box. 7.✅ Click the Group drop-down and ensure it contains the following group options: [Constitutional, Eyes, ENT, Respiratory, Cardiovascular, Gastrointestinal, Genitourinary (M/F), Musculoskeletal, Integumentary (Skin/Breast), Hematologic/Lymphatic/Immunologic, Endocrinology, Neurologic, Psychiatric, Allergic/Immunologic, Breastfeeding: Infant, Breastfeeding: Mother, Medical Home, Flu Immunization] 8.Type a custom question into the free-text box 9.✅ Verify that the text is accepted and auto-saved when the user navigates to another tab and then returns to the CC/HPI/ROS section. 10.Click the Add button. 11.✅ Verify that the newly added custom question appears under the selected ROS group. | C43: Yes | D43: Thara | G43: Thara
A44: Verify that staff can edit predefined HPI questions and answers using the Enter key. | B44: 1.Login as Nurse. 2.Click the Schedule icon under the Clinical tab. 3.Select the Tracking radio button. 4.Select the patient and open the Encounter Note. 5.Navigate to the CC/HPI/ROS page. 6.✅ Verify that predefined HPI questions are displayed with editable text boxes. 7.✅ Verify that the staff is able to edit the predefined template questions in the text box. 8.✅ Ensure that the staff can answer the HPI questions by typing the response and using the Enter button. | G44: Thara
A45: Verify that user can access and utilize Coordination of Care/Counseling functionality in encounter notes: 1. Open an encounter from the Schedule/Tracking Window. 2. Access the Couns/CoC tab in the visit note and verify the Counseling text box. 3. Verify the Counseling text box is available in the well visit note. | B45: 1.Login as Nurse. 2.Click the Schedule icon under the Clinical tab and select the Tracking radio button. 3.Select the patient and open the Encounter Note. 4.Navigate to the CC/HPI/ROS page. 5.✅ Verify that the staff can edit the ROS values based on the following mouse clicks: 5.1.Reports: 1 mouse click. 5.2.Denies: 2 mouse clicks. 5.3.Pert: 3 mouse clicks. | G45: Thara
A46: Verify that the user is able to see and click the Note Type on the Summary page of the Encounter Note. | B46: 1. Login as Nurse. 2. Click on the Patient Chart under the Clinical tab. 3. Select a patient using the Patient Finder. 4. Go to Encounter and click the New Note button. 5. Fill in the required fields (CC/HPI/ROS). 6. Navigate to the Summary page. 7. Verify that the user can view the Click Note Type on the Summary page ✅ User should see the Click Note Type in summary page on encounter note. | G46: Thara
A47: Verify that the Clinical Note Type displays the following options in order when the user clicks the Clinical Note Type button on the Summary page of the Encounter Note. | B47: 1. Login as Nurse. 2. Select patient using Patient Finder > Create new note (Encounter) 3. Fill required fields (CC/HPI/ROS) > Navigate to Summary page. 4. Verify Clinical Note Type options: - Progress Note, Consultation Note, History & Physical, Procedure Note, Imaging Narrative, Discharge Summary Note. ✅The Clinical Note Type should display the following options when the user clicks the Clinical Note Type button on the Summary page of the Encounter Note: | G47: Thara
A48: Verify that when the user selects the options below in Clinical Note Type on the Summary page, the LOINC code is reflected in the Database Viewer tab for the respective options for a patient on the Encounter Note. | B48: 1. Login as Nurse. 2. Select patient > Create new note (Encounter). 3. Fill required fields (CC/HPI/ROS) > Go to Summary page. 4. Select Clinical Note Type options: - Progress Note (11506-3), Consultation Note (11488-4), History & Physical (34117-2) Procedure Note (28570-0), Imaging Narrative (18748-4), Discharge Summary Note (18842-5) 5.Navigate to the Tools tab and open Database Viewer. 6. Click on the SQL tab and enter the following query (using the correct patient number): SELECT * FROM Enc_note WHERE patno = 9313; 5. Verify LOINC codes reflect in Database Viewer tab for Encounter note ✅The LOINC code should reflect in data base viewer tab for the respective options for a patient on encounter note. | G48: Thara
A49: Nurse Only Visit | B49: Nurse only visit(validate and verify functionalities in the vitals, allergies windows)
A50: Verify the staff is able to filter the patient based on nurse and doctor | B50: 1.Login as Nurse 2.navigate to tracking window 3.Select the Nursing from dropdown next to show task 4.Click the filter button next to staff dropdown 5.Select the Provider 6.✅Verify the list of patients based on Nurse and Provider | C50: Yes | D50: Thara | G50: Thara
A51: Verify staff can start a nurse visit and view vaccine list with stock availability in the Imm tab | B51: 1.Login as Nurse. 2.Add a new patient. 3.Search for the patient and create a "Nurse Only Visit" appointment by filling in all required fields. 4.Navigate to the Tracking window. 5.✅Ensure the patient appears in the Tracking window under the scheduled nurse visit. 6.Right-click on the patient and select Open Encounter. 7.Once in the encounter, navigate to the Plan/Orders tab from the left navigation. 8.Click on the Imm (Immunization) tab within the Plan/Orders section. 9.✅Verify that a list of available vaccine names is displayed. 10.✅Check that each listed vaccine has an available stock count (i.e., VFC and Private columns do not display N/A). 11.✅At the bottom of the Imm tab, verify that the VFC field is set to "No" by default. 12.✅Ensure that the VFC field is non-editable. | G51: Thara
A52: Verify end-to-end immunization task workflow for nurse visits | B52: 1.Login as Nurse. 2.Add a new patient (if needed). 3.Search for the patient and create a Nurse Only Visit appointment with the required fields. 4.Navigate to the Tracking Window. 5.Ensure the patient is listed in the Tracking Window. 6.Right-click the Patient Appointment and select Open Encounter. 7.Navigate to the Plan/Orders tab, then click the Imm tab. 8.Select the Today checkbox for one of the listed vaccines. 9.Click the Create button. 10.✅Verify a "Create Task for Immunization" confirmation popup is displayed. 11.Click OK on the confirmation popup. 12.✅Verify that the created immunization task is now listed in the View List with the status as "Not Started". 13.Go back to the Tracking Window. 14.Click the task column of the patient and select the pending Immunization Task. 15.✅Ensure the Immunization popup is displayed. 16.Fill in the required fields and click OK. 17.✅Verify the task count is decreased in the tracking window. 18.Right-click the patient again and select Open Encounter. 19.✅Click the Summary tab and verify that the immunization details are listed under the Primary Encounter Note tab. 20.Click the Finalize button. 21.✅Verify that a confirmation popup is displayed when clicking Finalize. 22.✅From the Tracking Window, update the Visit Status from Nurse: In Progress to Nurse: Finished. | G52: Thara
A53: Verify staff is able to create and finish a PPD visit for the patient | B53: 1.Login as Nurse. 2.Navigate to the Tracking Window. 3.Select the Patient Appointment with a PPD Visit Appointment. 4.Right-click on the patient appointment and select Open Encounter. 5.Make sure CC/HPI/ROS tab is displayed. 6.✅Review the existing data and add a comment including the latest PPD date and status.(in Detailed ROS). 7.Navigate to Visit info tab. 8.✅Verify that Rendering Provider is selected. 9.Go to the Plan/Orders tab, complete any required orders, and Save the note. 10.✅Verify that a PPD task is automatically created for the patient. 11.From the Tracking Window, select the PPD task from the task column. 12.In the PPD task window, fill out and save the requisition form. 13.✅Complete the Diagnostic Test Report. 14.✅Confirm that the Requisition Notes status changes to "Pending", and then close the diagnostic window. 15.Return to the Tracking Window. 16.Re-open the patient encounter and review the Summary Report. 17.✅Click Finalize to complete the summary. 18.✅Change the Visit Status to Nurse: Finished. | G53: Thara
A54: Verify staff can attend PPD reading, create PPD reading task, and finalize PPD documentation | B54: 1.Login as Nurse. 2.Navigate to the Tracking Window. 3.Right-click on the Patient Appointment scheduled for PPD reading and select Open Encounter. 4..Make sure CC/HPI/ROS tab is displayed. 5.Complete the CC (Chief Complaint) section and the associated Diagnostic Test. 6.✅Confirm that the Requisition Notes status updates to "Informed" upon completing the diagnostic test. 7.Navigate to Visit info tab. 8.✅Ensure a Rendering Provider is selected. 9.✅Navigate to the Summary tab and Finalize the encounter. 10.✅Change the Visit Status to Nurse: Finished in the Tracking Window. | G54: Thara
A55: Verify staff can add Medication, Allergies, and History for a new patient using the Patient Chart | B55: 1.Login as Nurse. 2.From the Calendar View, navigate to the My View section and select the patient appointment. 3.Click the Clinical tab. 4.Open the Patient Chart. 5.When the popup appears, click Cancel to bypass it. 6.In the Patient Chart, navigate to the Medication section and ✅add a new medication entry. 7.Navigate to the Allergies section and ✅add a new allergy entry. 8.Navigate to the History section and ✅add the patient’s medical history. | G55: Thara
A56: Verify staff can add patient immunization history using Quick Entry and use Copy Date feature | B56: 1.Login as Nurse. 2.Select a patient using patient chart. 3.From the left panel, click the Immunization tab. 4.In the Immunization window, click the Quick Entry button. 5.Select a vaccine name and enter the date. 6.Add a second vaccine entry in the next row. 7.In the Date field of the second vaccine, press the Spacebar to trigger the Copy Date feature. 8.✅Verify that the date from the first row is automatically copied into the second row’s date field. 9.Save the form. 10.Click the Refresh button in the Immunization window. 11.✅Verify that the newly added vaccines are displayed in the View List. | G56: Thara
A57: Verify staff can add previous measurements of the patient | B57: 1.Login as Nurse. 2.Select a patient using patient chart. 3.Select the Vitals/Growth section from the left panel. 4.Enter the required measurement values (e.g., height, weight, blood pressure) based on data from the last two visits. 5.Click Save to submit the measurements. 6.✅ Verify that the new measurements are saved successfully. 7.✅ Verify that the saved values correctly reflect the entries based on the patient’s previous two visits and are visible in the Vitals/Growth history. | G57: Thara
A58: Verify staff can create a new legacy and add multiple legacy labs for the patient | B58: 1. Login as Nurse. 2. Select a patient using patient chart. 3. Navigate to the Diagnosis window. 4. Click Add New Legacy. 5. Fill in the necessary fields (e.g., legacy details) for the first legacy. 6. Click the Save button at the bottom of the page. 7. ✅ Verify that the newly created legacy is saved successfully. 8. To add multiple legacy labs, repeat steps 4-6 for additional legacy entries. 9. ✅ Verify that multiple legacy labs can be added and saved successfully. | G58: Thara
A59: Verify staff can complete placeholder well visit for the patient | B59: 1. Login as Nurse. 2. Navigate to the Tracking Window. 3. Select the patient appointment scheduled for a Well Visit and change the Visit Status to reflect the appropriate status (e.g."In Progress"). 4. Open the Well Visit Window. 5. Click No in the confirmation window. 6. Click No for the default age template. 7. Ensure it navigates to the Summary Report Criteria Screen. 8. Click the Interval HX button. 9. Click the Complete List button and click the Well Visit Placeholder paperclip. 10. Click Close on the window and click No in the confirmation popup to add the DX code. 11. Click the Save button. 12. Navigate back to the Tracking Window. 13. Change the patient's status to MD: Patient Waiting. 14. ✅ Staff can successfully complete a placeholder well visit by following the steps and confirming correct navigation and data entry. | G59: Thara
A60: Verify staff can complete placeholder Encounter for the patient | B60: 1. Login as Nurse. 2. Navigate to the Tracking Window. 3. Select the patient appointment scheduled for an Encounter and change the Visit Status to reflect the appropriate status (e.g., "In Progress"). 4. Open the Encounter Window. 5. Click No in the confirmation window. 6. Ensure it navigates to the Summary Report Criteria Screen. 7. Click the CC/HPI/ROS Tab. 8. Search for the Encounter Placeholder Template from the "All Templates" field. 9. Click the Finalize button from the Summary Report and click Yes in the confirmation popup. 10. Change the Visit Status to MD: Patient Waiting. 11. ✅ Staff can successfully complete a placeholder encounter by finalizing the encounter and updating the visit status appropriately. | G60: Thara
A61: Verify staff can perform post-conversion actions for a patient for upcoming days | B61: 1.Login as Nurse. 2.From the Calendar View, select the patient appointment. 3.Click the Clinical button. 4.In the Clinical tab, click Medication. 5.For each listed medication, ✅ change the Chronic flag from N (No) to Y (Yes). 6.Navigate to Allergy and review the Allergies section—✅ verify all known allergies display correctly. 7.Navigate to Problem List and review the Problem List—✅ verify all active problems display correctly. 8.Navigate to Immunization and review the Immunization list—✅ verify all recorded immunizations display correctly. 9.Navigate to Vitals/Growth: 9.1.Click the Growth Measurement button. 9.2.In the growth measurement window, click Recalculate. 9.3.✅ Verify that the recalculated growth percentiles/values are populated correctly. | G61: Thara
A62: Verify the staff is able to do post conversion action for the patient for upcoming days | B62: 1.Login as Nurse 2.Select the patient from calendar view 3.click on Clinical button 4.Click on Medication from the clinical tab 5.Change the Chronic value from N to Y for listed medication 6.Review the Allergies 7.Review the problem list 8.Review the immunization list 9.Review the growth measurement I.To calculate the growth measurements using growth measurement button from vital sign window II.Click on recalculate button and make sure results are populated | G62: Thara
... A66: Verify the staff is able to scan the discharge document for the patient using page scan option | B66: 1.Login as Nurse 2.Click on clinical tab 3.Click on Document management icon 4.Click on New Note:if Confirm popup as Retain previous details? is displayed then click No 5.Click on Import Document button and select the page scanner button 7.Upload PDF is getting opened in preview page 8.Associate the patient with imported document 9.Click on save the document | G66: N/A
A67: Vitals/Growth Measurements
A68: The following scenarios should be covered under Encounter Note.
A69: Verify the Vitals/Growth tabs UI and Data Entry Functionalities | B69: 1. Login as Nurse 2. Click the schedule icon and click the tracking radio button. 3. Select a scheduled appointment for a patient and right-click using the mouse. 4. Click "Open well visit" option and navigate to "Vital/Growth" tab. 5. Click the following tabs and verify they are accessible: 5.1. ✅ Vital Growth → Make sure the Vital Sign page is accessible. 5.2. ✅ Ensure Add, Edit, and Delete buttons are clickable by default in the Vital Sign section. 5.3. ✅ Ensure Save and Cancel buttons are disabled by default in the Vital Sign section. 5.4. Click the "ADD" button in the Vital Sign section and verify the following actions can be performed: 5.5.1. ✅ Ensure "TYMP" is selected by default in the Temp Method field. 5.5.2. ✅ Ensure the user can update the Temp Method field by selecting options: [Tymp, Skin, Oral, Axillary, T/A, Rectal]. 5.5.3 Enter values for the following fields and ✅ verify the calculator dropdown is functional: [Temperature, BP Systolic, BP Diastolic, Pulse, Respiratory Rate, Pulse Ox, Peak Flow]. 5.5.4. ✅ Ensure Temperature is set to Fahrenheit (°F) by default. 5.5.5. ✅ Ensure "Sit/Stand" is selected as the default BP method. | C69: Yes | D69: Thara | G69: Thara
A70: Verify the Growth tabs UI and Data Entry Functionalities | B70: 1. Login as Nurse 2. Click the schedule icon and click the tracking radio button. 3. Select a scheduled appointment for a patient and right-click using the mouse. 4. Click "Open well visit" option and navigate to "Vital/Growth" tab. 5. Click the following tabs and verify they are accessible: 5.1. ✅ Ensure Patient age is displayed in the Growth Measurements section of the Vital Sign. 5.2. ✅ Ensure the New, Delete, Edit, and Refresh buttons are displayed in the Growth Measurements section. 5.3. Click the "ADD" button in the Growth Measurement section and ✅ verify the following actions can be performed: 5.3.1. ✅ Make sure WHO/CDC (practice setting) is selected as default under Growth Measurement section. 5.3.2. Enter values for the following fields and ✅ verify the calculator dropdown is functional: [Stature/Length (in and cm), Weight (lb and oz and kg), Head circumference (in and cm), mid-parental height mother (in), mid-parental height father (in), mid-parental height predicted (in)]. 5.3.3. ✅ Verify the user can select/unselect the "Exclude from charts" checkbox. | C70: Yes | D70: Thara | G70: Thara
A71: Verify the default value and editability of the Date/Time Taken field under Vital Signs. | B71: 1. Log in as a Nurse. 2. Click the Schedule icon and select the Tracking radio button. 3. Select a scheduled appointment for a patient and right-click using the mouse. 4. Click the "Open Well Visit" option. 5. Click on the "Vitals/Growth" option. 6. The Vital Signs page should be displayed. 7. Click the "New" button. 7.1. ✅Verify that the current date and time are automatically populated in the Date/Time Monitored field. 7.2. ✅Modify the populated date and time manually. 7.3. ✅Verify that the system allows the date and time to be updated successfully. | C71: Yes | D71: Thara | G71: Thara
A72: Verify User able to Add Vital sign | B72: 1.Log in as Nurse. 2. Click the Schedule icon and select Tracking Radio Button. 3.Select a patient appointment, right-click, and choose "Open Well Visit". 4. Click "Vitals/Growth". 5. The Vital Sign Page should display. 6. Click "New" button and✅ ensure user able to perform following actions: 6.1. Enter a numeric value in the Temperature field and text in the Temperature Notes field. 6.2. Enter a numeric value in the BP Systolic field and text in the BP Systolic Notes field. 6.3. Enter a numeric value in the BP Diastolic field and text in the BP Diastolic Notes field. 6.4. Enter a numeric value in the Pulse(Heart Rate) field and text in the Pulse(Heart Rate) Notes field. 6.5. Enter a numeric value in the Respiratory Rate field and text in the Respiratory Rate Notes field. 6.6. Enter a numeric value in the Pulse ox field and text in the Pulse ox Notes field. 6.7. Enter a numeric value in the Pulse flow field and text in the Pulse flow Notes field. 6.8. Enter a numeric value in the Severity of pain field and text in the Severity of pain Notes field. 6.9. Click + button →✅ Make sure user able to add new Other Measurement 7.Click save button →✅ Make sure save doesn't show any popup confirmation message | G72: Thara
A73: Verify User able to Edit Vital Sign | B73: 1.Log in as a Nurse. 2.Click the Schedule icon and select the Tracking radio button. 3.Select a patient appointment, right-click, and choose "Open Well Visit". 4.Click "Vitals/Growth". 5.The Vital Sign Page should display. 6.Select an existing vital sign entry. 7.Click the "Edit" button and ensure user able to perform following actions: 7.1. Ensure waring prompt appears: "Do you want to Edit vital sign entered on MM/DD/YYYY HH:MM XX?" 7.1.1. If yes, the user should be allowed to modify and save the vital sign entry. 7.2. Edit numeric value in the Temperature field and text in the Temperature Notes field. 7.3. Edit numeric value in the BP Systolic field and text in the BP Systolic Notes field. 7.4. Edit numeric value in the BP Diastolic field and text in the BP Diastolic Notes field. 7.5. Edit numeric value in the Pulse(Heart Rate) field and text in the Pulse(Heart Rate) Notes field. 7.6. Edit numeric value in the Respiratory Rate field and text in the Respiratory Rate Notes field. 7.7. Edit numeric value in the Pulse ox field and text in the Pulse ox Notes field. 7.8. Edit numeric value in the Pulse flow field and text in the Pulse flow Notes field. 7.9. Edit numeric value in the Severity of pain field and text in the Severity of pain Notes field. 8.Click save button → Make sure save doesn't show any popup confirmation message | C73: Yes | D73: Thara | G73: Thara
A74: Verify User Can Cancel Vital Signs (Standard & Other Measurements) Before Saving with Confirmation | B74: 1.Log in as a Nurse. 2.Click the Schedule icon and select the Tracking radio button. 3.Select a patient appointment, right-click, and choose "Open Well Visit". 4.Click "Vitals/Growth". 5.The Vital Sign Page should display. 6.Click New button and enter Standard Measurements & Other measurements values. 7.Click Cancel Button. 8.✅ Verify that a confirmation pop-up appears with the message: "Are you sure you want to cancel? Unsaved changes will be lost." 8.1. If user selects Yes → verify that the entered data is discarded. 8.2. If user selects No → verify that the user remains on the page with entered values intact. | C74: Yes | D74: Thara | G74: Thara
A75: Verify User Can Delete Vital Signs (Standard & Other Measurements) with Confirmation | B75: 1.Log in as a Nurse. 2.Click the Schedule icon and select the Tracking radio button. 3.Select a patient appointment, right-click, and choose "Open Well Visit". 4.Click "Vitals/Growth". 5.The Vital Sign Page should display. 6.Select an existing vital sign entry. 7.Click the Delete button. 8.✅ Verify that a confirmation pop-up appears with the message: "Are you sure you want to delete this vital sign entry?" 8.1. If user selects Yes → verify that the vital sign entry is removed. 8.2. If user selects No → verify that the vital sign entry remains intact. | C75: Yes | D75: Thara | G75: Thara
A76: Pre-condition: Height should not be entered while saving vitals/signs Verify that "Need Height" appears in Vitals/Signs when entering BP values for patients under 18 years | B76: 1. Log in to OP with valid credentials. 2. Create a new patient under 18 years of age. 3. Navigate to the Vitals/Growth tab. 4. Select New under Vital signs. 5. Enter BP systolic: (i.e)110, BP diastolic:(i.e: 72), pulse:(i.e: 68). 6. Click Save. 7. Verify that the "Need Height" message is displayed. 8. Select New under Growth Measurements. 9. Enter Stature: (i.e: 52.95), Weight:(i.e: 63). 10. Click Save. 11. Verify that the vitals screen refreshes automatically with accurate BP percentiles. Expected Results: - ✅"Need Height" should appear when vitals are saved for patients under 18 years. - ✅Vitals screen should refresh automatically after saving growth measurements and display correct BP percentiles. | C76: yes | D76: Thara | G76: Thara
A77: Verify Date/Time Monitored Field in Growth Measurements | B77: 1.Log in as a Nurse. 2.Click the Schedule icon and select the Tracking radio button. 3.Select a patient appointment, right-click, and choose "Open Well Visit" 4.Click the "Vitals/Growth" tab. 5.Open the Growth Measurements window. 6.Click the New button. 7.✅ Verify that the current Date and Time is automatically populated in the Date/Time Monitored field. 8.Edit the Date/Time Monitored field and enter a different date/time. 9.✅ Verify the modified date/time is saved successfully. | G77: Thara
A78: Verify User able to Add Growth Measurement | B78: 1.Log in as Nurse. 2. Click the Schedule icon and select Tracking Radio Button. 3.Select a patient appointment, right-click, and choose "Open Well Visit" 4. Click "Vitals/Growth". 5. The Vital Sign Page should display. 6. Click "New" button and ✅ ensure user able to perform following actions: 6.1 Enter a numeric value in the Stature/Length field 6.1.1. Enter a value in inches (in) and verify it is correctly converted to centimeters (cm). 6.1.2. Enter a value in centimeters (cm) and verify it is correctly converted to inches (in). 6.2 Enter a numeric value in the weight field 6.2.1. Enter a value in lb and oz and verify it is correctly converted to Kg. 6.2.2. Enter a value in kg and verify it is correctly converted to lb and oz. 6.3. Enter a numeric value in the head circumference field and ✅ ensure user should be filled for the younger age patients (below 2 yr) 6.3.1. Enter a value in inches (in) and verify it is correctly converted to centimeters (cm). 6.3.2. Enter a value in centimeters (cm) and verify it is correctly converted to inches (in). 6.4. Enter a numeric value in the mid-parental height mother field 6.5. Enter a numeric value in the mid-parental height father field 6.6. Enter a numeric value in the mid-parental height predicted field 6.7. ✅ Verify user can enter comments in the comment field. 7.Click save button. 8. ✅ Verify the percentile and BMI value is auto populated | C78: Yes | D78: Thara | G78: Thara
A79: Verify User able to Edit Growth Measurement | B79: 1.Log in as a Nurse. 2.Click the Schedule icon and select the Tracking radio button. 3.Select a patient appointment, right-click, and choose "Open Well Visit" 4.Click "Vitals/Growth". 5.The Vital Sign Page should display. 6.Select an existing vital sign entry. "Open Well Visit" 7.Click the "Edit" button and ✅ ensure user able to perform following actions: 7.1. ✅ Ensure waring prompt appears: "You are about to EDIT measurements entered on: MM/DD/YYYY Do you wish to continue?" 7.1.1 If yes, the user should be allowed to modify and save the vital sign entry. 7.2. Edit numeric value in the Stature/Length field 7.3. Edit numeric value in the weight field 7.4. Edit numeric value in the head circumference field 7.5. Edit numeric value in the mid-parental height mother field 7.6. Edit numeric value in the mid-parental height father field 7.7. Edit numeric value in the mid-parental height predicted field 7.8.✅ Verify user can edit comments in the comment field. 8.Click save button. | C79: Yes | D79: Thara | G79: Thara
A80: Verify user can Cancel Growth Measurements prior to Save | B80: 1. Login as Nurse 2. Click the schedule icon and click the tracking radio button. 3.Select a patient appointment, right-click, and choose "Open Well Visit" 4. Click "Open well visit" option and click the "Vitals/Growth" option 5. Vital sign page should display and navigate to "growth measurement tab" 6. Click new button and type growth measurement value 7. Click on cancel button 8. ✅ Make sure the changes are reverted back to the previously entered value. | G80: Thara
A81: Verify User Can Delete Growth Measurements with Confirmation | B81: 1.Log in as a Nurse. 2.Click the Schedule icon and select the Tracking radio button. 3.Select a patient appointment, right-click, and choose "Open Well Visit" 4.Click "Vitals/Growth". 5.The Vital Sign Page should display. 6.Select an existing Growth Measurement entry. 7.Click the Delete button. 8.✅ Verify that a confirmation pop-up appears with the message: "Are you sure you want to delete this vital sign entry?" 8.1. If user selects Yes → verify that the vital sign entry is removed. 8.2. If user selects No → verify that the vital sign entry remains intact. | C81: Yes | D81: Thara | G81: Thara
A82: Verify the weight table is display Ounces to lbs listed as it was in the graph of Growth chart. | B82: 1. Login to OP with valid credentials. 2. Click the Clinical tab and access the Patient Chart window. 3. Search for the patient in the search box and select the patient. 4. Click Vitals/Growth. 5. The Vital Signs page should display. 6. Go to Growth Chart. 7. Select the following three types under Chart Type: Stature/Age, Length/Age, Weight/Age. 8. Click the Print button and zoom in on the print page. 9. ✅ Observe the weight table to confirm that ounces to lbs are listed, matching the graph. | G82: Thara
A83: Verify the Growth Charts tab data is populated | B83: 1. Login as Nurse 2. Click the schedule icon and click the tracking radio button. 3.Select a patient appointment, right-click, and choose "Open Well Visit" 4. Click "Open well visit" option and click the "Vitals/Growth" option 5. Vital sign page should display 6. Navigate to growth chart screen 7. ✅ Make sure newly added data are populated in growth chart tab | C83: Yes | D83: Thara | G83: Thara
A84: Verify the Growth Measurements is populated | B84: 1. Login as Nurse 2. Click the schedule icon and click the tracking radio button. 3.Select a patient appointment, right-click, and choose "Open Well Visit" 4. Click "Open well visit" option and click the "Vitals/Growth" option 5. Vital sign page should display 6. Navigate to growth Measurements screen 7.✅ Make sure newly added data are populated in growth Measurements tab | C84: Yes | D84: Thara | G84: Thara
A85: Verify the Vital Signs Charts data is populated | B85: 1. Login as Nurse 2. Click the schedule icon and click the tracking radio button. 3.Select a patient appointment, right-click, and choose "Open Well Visit" 4. Click "Open well visit" option and click the ""Vitals/Growth" " option 5. Vital sign page should display 6. Navigate to Vital Signs Charts screen 7.✅ Make sure newly added data are populated in Vital Signs Charts tab | C85: Yes | D85: Thara | G85: Thara
A86: Add the 3 vital sign in different time in same day. Verify the newly added vitals in the summary section. | B86: 1.Login as Nurse 2.Click the schedule icon and click the tracking radio button. 3.Select a patient appointment, right-click, and choose "Open Well Visit" 4. Click "Open well visit" option 5. Click on Vitals/Growth 6. Add 3 vital sign with different time(ex: 12:40, 12:55, 13:10)and save the record. 7. Click the summary tab in the bottom of the section. 8. ✅ Verify all 3 vitals should display in the vital section with 12 hours time format. | C86: Yes | D86: Thara | G86: Thara
A87: Verify vitals added at different times on the same day display correctly in Medical Record section and Print preview | B87: 1. Login as Nurse 2. Go to a patient chart 3. Click on Vitals/Growth 4. Add 3 vital sign with different time(ex: 12:40, 12:55, 13:10)and save the record. 5. Navigate to medical record 6. ✅ Verify all 3 vitals should display in the medical record section with 12 hours time format. 7. Click the Print button in the Medical Record section. 8. ✅ Verify all the 3 vitals(include time with 12 hours formats) should display in the print sections. | C87: Yes | D87: Thara | G87: Thara
A88: Verify LOINC Codes for Various Measurements in Vitals/Growth Tab | B88: 1. Login as Nurse 2. Click Patient Chart under the Clinical tab. 3. Select a patient using the Patient Finder. 4. Navigate to the Vitals/Growths tab. 5. Open the Growth Measurements section. 6. Click the New button. 7. Select the appropriate radio button and enter high values for the following fields: 7.1. Stature (if selected, should store LOINC code 8308-9). 7.2. Length (if selected, should store LOINC code 8306-3). 7.3. Weight (should store LOINC code 29463-7). 7.4. BMI Percentile (should store LOINC code 59576-9). 7.5. Weight-for-Length Percentile (should store LOINC code 77606-2). 7.6. Head Occipital-frontal Circumference Percentile (should store LOINC code 8287-5). 8. Click the Save button. 9. Navigate to the Tools tab and open Database Viewer. 10. Click on the SQL tab and enter the following query (using the correct patient number): SELECT * FROM physical_chart WHERE patno = 9313; 11. Click Run. 12. ✅ Verify that the corresponding LOINC codes appear correctly in the database viewer tab for the patient. | G88: Thara
A89: Verify user able to print the Growth charts on Vitals/Growth tab | B89: 1. Login as Nurse. 2.Click Patient chart under Clinical tab. 3.Select a patient using patient finder. 4.Navigate to Vitals/Growth tab and Go to Growth Charts tab. 5.Click print button 6.✅ Make sure that print preview window should open. | C89: Yes | D89: Thara | G89: Thara
A90: Verify that user able to see the added and updated Vitals/Growth in the summary page. | B90: 1. Login as Nurse. 2. Click the schedule icon and click the tracking radio button. 3. Select a new patient and right-click the patient using the mouse. 4. Click "Open well visit" option. 5. Navigate to the vital/growth tab. 6. Add new vital/growth and save it. 7. Scroll down to the bottom and click the summary section. ✅ Added vital/growth should display on the summary page. 8. Repeat steps 1-5, update the existing vital/growth, and save it. 9. Scroll down to the bottom and click the summary section. ✅ Updated vital/growth details should display on the summary page. | C90: Yes | D90: Thara | G90: Thara
A91: Verify the deleted Vitals/Growth shouldn't display in the summary page. | B91: 1. Login as Nurse. 2. Click the Schedule icon and select the Tracking radio button. 3. Select a new patient and right-click on the patient using the mouse. 4. Click the "Open Well Visit" option. 5. Navigate to the Vital/Growth tab. 6. Delete a vital/growth entry and save the changes. 7. Scroll down to the bottom and click on the Summary section. ✅ Deleted vital/growth details should not display on the summary page. | C91: Yes | D91: Thara | G91: Thara
A92: Verify user receives Confirm window prior to Cancel | B92: 1. Login as Nurse 2. Click the schedule icon and click the tracking radio button 3. Select a patient appointment, right-click, and choose "Open Well Visit" 4. Click the "Open Well Visit" option and click the "Vitals/Growth" tab 5. Vital Sign page should display and navigate to the Growth Measurement tab 6. Click the New button and enter Growth Measurement values 7. Click the Cancel button ✅ Verify that a cancel confirmation popup is displayed | G92: Thara
A93: Verify when user enters new vitals in Celsius as 39.0 and clicks save, the entry will change to 102.2 in F and should remain in red H(high). | B93: 1. Login as Nurse. 2. Click the Clinical tab and access the patient chart. 3. Search and select the patient using Patient Finder. 4. Click Vitals/Growth under the Clinical section. 5. Access the Enter Vital Signs tab on the Vitals/Growth page. 6. Click the New button. In the Temperature field, select the C (Celsius) radio button. 7. Enter 39.0°C in the Temperature field and click the Save button. ✅ 8. Verify that the entry is converted to 102.2°F and is displayed in red with 'H' (High) indicator. | C93: Yes | D93: N/A | G93: N/A
A94: Verify when user enters new vitals in Celsius as 25.0 and clicks save, the entry will change to 77 in F and should remain in blue L(low). | B94: 1. Login as Nurse. 2. Click the Clinical tab and access the patient chart. 3. Search and select the patient using Patient Finder. 4. Click Vitals/Growth under the Clinical section. 5. Access the Enter Vital Signs tab on the Vitals/Growth page. 6. Click the New button. In the Temperature field, select the C (Celsius) radio button. 7. Enter 25.0°C in the Temperature field and click the Save button. ✅ 8. Verify that the entry is converted to 77.0°F and is displayed in blue with "L" (Low) indicator. | C94: Yes | D94: N/A | G94: N/A
A95: Verify when user edits existing vitals and entering Celsius as 38.0 and clicks save, the entry will change to 100.4 in F and should remain in red H(high). | B95: 1. Login as Nurse. 2. Click the Clinical tab and access the patient chart. 3. Search and select the patient using Patient Finder. 4. Click Vitals/Growth under the Clinical section. 5. Access the Enter Vital Signs tab on the Vitals/Growth page. 6. Choose an existing vitals entry and click the Edit button. In the Temperature field, select the C (Celsius) radio button. 7. Enter 38.0°C in the Temperature field and click the Save button. ✅ 8. Verify that the entry is converted to 100.4°F and is displayed in red with 'H' (High) indicator. | C95: Yes | D95: N/A | G95: N/A
A96: Verify when user edits existing vitals and entering Celsius as 30.0 and clicks save, the entry will change to 86 in F and should remain in blue L(low). | B96: 1. Login as Nurse. 2. Click the Clinical tab and access the patient chart. 3. Search and select the patient using Patient Finder. 4. Click Vitals/Growth under the Clinical section. 5. Access the Enter Vital Signs tab on the Vitals/Growth page. 6. Choose an existing vitals entry and click the Edit button. In the Temperature field, select the C (Celsius) radio button. 7. Enter 30.0°C in the Temperature field and click the Save button. ✅ 8. Verify that the entry is converted to 86°F and is displayed in blue with L (Low) indicator. | C96: Yes | D96: N/A | G96: N/A
A97: Verify the Patient Register: Note and Coordination care window is open, when user click the Transmit icon on Print preview window. | B97: 1. Login as Nurse. 2. Click Patient Chart under the Clinical tab. 3. Select a patient using Patient Finder. 4. Navigate to the Vitals/Growth tab and go to the Growth Charts tab. 5. Click the Print button. ✅ 6. Verify that the Print Preview window opens. 7. Click the Transmit icon on the Print Preview window. ✅ 8. Verify that the Patient Register: Note and Coordination Care window opens. | G97: Thara
A98: Verify the patient details are Auto filled in Message window, when user click the Transmit icon on Print preview and Click save button on Patient Register: Note and Coordination care window. | B98: 1. Login as Nurse. 2. Click Patient Chart under the Clinical tab. 3. Select a patient using Patient Finder. 4. Navigate to the Vitals/Growth tab and go to the Growth Charts tab. 5. Click the Print button. ✅ 6. Verify that the Print Preview window opens. 7. Click the Transmit icon on the Print Preview window. ✅ 8. Verify that the Patient Register: Note and Coordination Care window opens. 9. Click the Save button. ✅ 10. Verify that the Message window opens. ✅ 11. Verify that the Patient details are auto-filled in the Message tab. | G98: Thara
A99: Problem List
A100: The following scenarios should be covered under Well Visit Note
